Workbook

Sheet Leyenda
A1: Evaluación de trabajos de grado – Capítulos 1 y 2
A2: MI131 Metodología de Investigación · Administración Deportiva · Universidad Distrital · Segundo corte (carpeta 19 07102026) · Evaluación realizada el 19/10/2026
A4: Propósito | B4: Evaluar los 11 documentos (G1 – G11) en los ítems: descripción del problema, pregunta problema, objetivo general, objetivos específicos, justificación, antecedentes y marco teórico (capítulo 2), más redacción y normas APA 7.ª edición como criterio transversal. Se entregan análisis cuantitativo y cualitativo, con los errores de elaboración por ítem.
A5: Cómo se calcula | B5: Cada uno de los 31 indicadores se codifica 0 (no cumple), 1 (cumple parcialmente) o 2 (cumple). Nota del ítem = Σ(peso del indicador × código / 2) × 5. Nota total = Σ(peso del ítem × nota del ítem). Los pesos y parámetros están en la hoja Rúbrica; al modificarlos, todas las hojas se recalculan.
A6: Escala y niveles | B6: Escala 0 – 5. Umbral de logro y puntos de corte de los niveles (Alto, Satisfactorio, En desarrollo, Insuficiente) en la hoja Rúbrica, celdas D5 – D8.
A7: Código de colores | B7: Azul sobre fondo amarillo: dato de entrada o juicio del evaluador (editable). Negro: fórmula. Verde: enlace a otra hoja. Rojo / amarillo / verde en celdas: condiciones por debajo del umbral, intermedias o logradas.
A8: Orden de las hojas | B8: Leyenda · Rúbrica · Calificación (31 indicadores × 11 grupos) · Análisis cuantitativo · Análisis cualitativo (88 celdas grupo × ítem) · Errores APA y redacción · Coherencia interna · Resumen por grupo · Declaración de IA.
A9: Supuestos | B9: Se evaluó únicamente el texto entregado en cada archivo .docx. No se evaluó la metodología del capítulo 3 ni los instrumentos, salvo cuando el capítulo 2 o los objetivos remiten a ellos para comprobar la coherencia. Los pesos de la rúbrica son una propuesta del evaluador y pueden ajustarse a la rúbrica oficial del curso.
A10: Límites de la verificación | B10: La correspondencia entre citas y referencias se revisó con un script y lectura manual. Solo se consultaron en línea las referencias señaladas en la hoja Declaración de IA; las demás no se contrastaron con la fuente original. No se utilizó software de similitud: las observaciones de originalidad son indicios por revisar con la herramienta institucional.
A11: Uso de las notas | B11: Las notas son una propuesta de calificación sujeta a validación del profesor. Los comentarios son aptos para devolverlos a los estudiantes: están redactados en términos verificables, con ubicación y ejemplo del error.
A13: Resultados clave
A14: Grupos evaluados | B14: =COUNTA('Resumen por grupo'!A5:A15) -> 11
A15: Nota media del curso (0 – 5) | B15: ='Análisis cuantitativo'!D27 -> 3.3860227
A16: Grupos que alcanzan el umbral | B16: ='Análisis cuantitativo'!I27 -> 8
A17: Mayor nota (grupo) | B17: ='Análisis cuantitativo'!K27 -> G7
A18: Menor nota (grupo) | B18: ='Análisis cuantitativo'!L27 -> G5
A19: Hallazgos APA / redacción registrados | B19: ='Errores APA y redacción'!M14 -> 104
A20: Controles de la hoja de cálculo | B20: =IF(AND(Rúbrica!C19=1,Calificación!E47>=0,'Errores APA y redacción'!M21="OK"),"OK","REVISAR") -> OK

Sheet Rúbrica
A1: Rúbrica de evaluación – Capítulos 1 y 2 de la monografía
A2: Escala de cada indicador: 0 = ausente o con error grave; 1 = cumple parcialmente; 2 = cumple. Los pesos (azul) son parámetros editables.
A4: Parámetros
A5: Escala máxima de nota | D5: 5
A6: Umbral de logro (nota mínima) | D6: 3
A7: Nivel «Alto» desde | D7: 4
A8: Nivel «En desarrollo» desde | D8: 2
A10: Código | B10: Ítem evaluado | C10: Peso del ítem
A11: P | B11: Descripción del problema | C11: 0.18
A12: Q | B12: Pregunta problema | C12: 0.14
A13: OG | B13: Objetivo general | C13: 0.09
A14: OE | B14: Objetivos específicos | C14: 0.09
A15: J | B15: Justificación | C15: 0.13
A16: A | B16: Antecedentes (Capítulo 2) | C16: 0.14
A17: M | B17: Marco teórico y conceptual (Capítulo 2) | C17: 0.13
A18: T | B18: APA 7 y redacción (transversal) | C18: 0.1
B19: Suma de pesos (debe ser 100 %) | C19: =SUM(C11:C18) -> 1
A21: Indicadores
A22: Ítem | B22: Código | C22: Indicador (criterio de cumplimiento pleno = 2) | D22: Peso en el ítem | E22: Peso global | F22: Suma de pesos del ítem | G22: Verificación
A23: P | B23: P1 | C23: Contextualiza el problema en los niveles internacional, nacional y local con fuentes verificables | D23: 0.25 | E23: =SUMIF($A$11:$A$18,A23,$C$11:$C$18)*D23 -> 0.045 | F23: =SUM(D23:D27) -> 1 | G23: =IF(ROUND(F23,4)=1,"OK","Revisar") -> OK
A24: P | B24: P2 | C24: Presenta la magnitud con datos cuantitativos verificables y atribuidos correctamente a la fuente | D24: 0.25 | E24: =SUMIF($A$11:$A$18,A24,$C$11:$C$18)*D24 -> 0.045
A25: P | B25: P3 | C25: Describe causas y consecuencias, con sustento, y quiénes resultan afectados | D25: 0.2 | E25: =SUMIF($A$11:$A$18,A25,$C$11:$C$18)*D25 -> 0.036
A26: P | B26: P4 | C26: Delimita el vacío o la brecha de conocimiento que origina el estudio | D26: 0.15 | E26: =SUMIF($A$11:$A$18,A26,$C$11:$C$18)*D26 -> 0.027
A27: P | B27: P5 | C27: Redacción: claridad, registro académico, coherencia y ausencia de redundancias | D27: 0.15 | E27: =SUMIF($A$11:$A$18,A27,$C$11:$C$18)*D27 -> 0.027
A28: Q | B28: Q1 | C28: Se formula como interrogante único, claro y abierto, sin respuesta sí/no ni valorativa | D28: 0.3 | E28: =SUMIF($A$11:$A$18,A28,$C$11:$C$18)*D28 -> 0.042 | F28: =SUM(D28:D31) -> 1 | G28: =IF(ROUND(F28,4)=1,"OK","Revisar") -> OK
A29: Q | B29: Q2 | C29: Delimita objeto, población, lugar y tiempo | D29: 0.3 | E29: =SUMIF($A$11:$A$18,A29,$C$11:$C$18)*D29 -> 0.042
A30: Q | B30: Q3 | C30: Es coherente con el problema planteado (responde al vacío enunciado) | D30: 0.2 | E30: =SUMIF($A$11:$A$18,A30,$C$11:$C$18)*D30 -> 0.028
A31: Q | B31: Q4 | C31: Es investigable y viable con los recursos y datos disponibles | D31: 0.2 | E31: =SUMIF($A$11:$A$18,A31,$C$11:$C$18)*D31 -> 0.028
A32: OG | B32: G1 | C32: Verbo en infinitivo, medible, un solo propósito, sin incluir método | D32: 0.35 | E32: =SUMIF($A$11:$A$18,A32,$C$11:$C$18)*D32 -> 0.0315 | F32: =SUM(D32:D34) -> 1 | G32: =IF(ROUND(F32,4)=1,"OK","Revisar") -> OK
A33: OG | B33: G2 | C33: Responde a la pregunta problema (misma población, variables y alcance) | D33: 0.35 | E33: =SUMIF($A$11:$A$18,A33,$C$11:$C$18)*D33 -> 0.0315
A34: OG | B34: G3 | C34: Incluye la delimitación (población, contexto, periodo) | D34: 0.3 | E34: =SUMIF($A$11:$A$18,A34,$C$11:$C$18)*D34 -> 0.027
A35: OE | B35: E1 | C35: Verbos en infinitivo y medibles; un resultado de conocimiento por objetivo (no pasos del procedimiento) | D35: 0.3 | E35: =SUMIF($A$11:$A$18,A35,$C$11:$C$18)*D35 -> 0.027 | F35: =SUM(D35:D37) -> 1 | G35: =IF(ROUND(F35,4)=1,"OK","Revisar") -> OK
A36: OE | B36: E2 | C36: Derivan del objetivo general y lo cubren sin exceder su alcance | D36: 0.35 | E36: =SUMIF($A$11:$A$18,A36,$C$11:$C$18)*D36 -> 0.0315
A37: OE | B37: E3 | C37: Secuencia lógica y alcance viable para una monografía | D37: 0.35 | E37: =SUMIF($A$11:$A$18,A37,$C$11:$C$18)*D37 -> 0.0315
A38: J | B38: J1 | C38: Justificación académica o teórica vinculada con el vacío de conocimiento | D38: 0.25 | E38: =SUMIF($A$11:$A$18,A38,$C$11:$C$18)*D38 -> 0.0325 | F38: =SUM(D38:D41) -> 1 | G38: =IF(ROUND(F38,4)=1,"OK","Revisar") -> OK
A39: J | B39: J2 | C39: Justificación social y práctica para la gestión deportiva, con destinatarios identificados | D39: 0.25 | E39: =SUMIF($A$11:$A$18,A39,$C$11:$C$18)*D39 -> 0.0325
A40: J | B40: J3 | C40: Pertinencia y viabilidad del estudio (acceso, tiempo, recursos) | D40: 0.25 | E40: =SUMIF($A$11:$A$18,A40,$C$11:$C$18)*D40 -> 0.0325
A41: J | B41: J4 | C41: Sustento con fuentes y redacción sin afirmaciones no respaldadas | D41: 0.25 | E41: =SUMIF($A$11:$A$18,A41,$C$11:$C$18)*D41 -> 0.0325
A42: A | B42: A1 | C42: Pertinencia, actualidad y calidad de las fuentes | D42: 0.3 | E42: =SUMIF($A$11:$A$18,A42,$C$11:$C$18)*D42 -> 0.042 | F42: =SUM(D42:D45) -> 1 | G42: =IF(ROUND(F42,4)=1,"OK","Revisar") -> OK
A43: A | B43: A2 | C43: Estructura de la reseña: objetivo, método, resultados y aporte al estudio | D43: 0.25 | E43: =SUMIF($A$11:$A$18,A43,$C$11:$C$18)*D43 -> 0.035
A44: A | B44: A3 | C44: Síntesis crítica de los antecedentes y brecha formulada | D44: 0.3 | E44: =SUMIF($A$11:$A$18,A44,$C$11:$C$18)*D44 -> 0.042
A45: A | B45: A4 | C45: Cobertura de niveles (internacional, nacional y local) | D45: 0.15 | E45: =SUMIF($A$11:$A$18,A45,$C$11:$C$18)*D45 -> 0.021
A46: M | B46: M1 | C46: Desarrolla las categorías o variables del problema con definiciones | D46: 0.3 | E46: =SUMIF($A$11:$A$18,A46,$C$11:$C$18)*D46 -> 0.039 | F46: =SUM(D46:D49) -> 1 | G46: =IF(ROUND(F46,4)=1,"OK","Revisar") -> OK
A47: M | B47: M2 | C47: Autores y fuentes de base pertinentes (primarias, no solo secundarias) | D47: 0.25 | E47: =SUMIF($A$11:$A$18,A47,$C$11:$C$18)*D47 -> 0.0325
A48: M | B48: M3 | C48: Articulación del marco con la pregunta, los objetivos y el diseño | D48: 0.25 | E48: =SUMIF($A$11:$A$18,A48,$C$11:$C$18)*D48 -> 0.0325
A49: M | B49: M4 | C49: Paráfrasis, redacción y cohesión; sin fragmentos sin fuente | D49: 0.2 | E49: =SUMIF($A$11:$A$18,A49,$C$11:$C$18)*D49 -> 0.026
A50: T | B50: T1 | C50: Citas en texto con formato APA 7 (narrativas y parentéticas, et al., secundarias) | D50: 0.25 | E50: =SUMIF($A$11:$A$18,A50,$C$11:$C$18)*D50 -> 0.025 | F50: =SUM(D50:D53) -> 1 | G50: =IF(ROUND(F50,4)=1,"OK","Revisar") -> OK
A51: T | B51: T2 | C51: Correspondencia entre citas y lista de referencias (sin huérfanas ni faltantes) | D51: 0.3 | E51: =SUMIF($A$11:$A$18,A51,$C$11:$C$18)*D51 -> 0.03
A52: T | B52: T3 | C52: Lista de referencias en formato APA 7 (autor, orden, DOI/URL, sin duplicados) | D52: 0.25 | E52: =SUMIF($A$11:$A$18,A52,$C$11:$C$18)*D52 -> 0.025
A53: T | B53: T4 | C53: Ortografía, estilo, plantilla institucional y declaración de uso de IA | D53: 0.2 | E53: =SUMIF($A$11:$A$18,A53,$C$11:$C$18)*D53 -> 0.02
C54: Suma de pesos globales (debe ser 100 %) | E54: =SUM(E23:E53) -> 1

Sheet Calificación
A1: Calificación por indicador (0 – 1 – 2) y nota por ítem
A2: Celdas azules = códigos asignados por el evaluador. Las notas por ítem y la nota total se calculan con fórmulas a partir de los pesos de la hoja Rúbrica.
A4: Ítem | B4: Código | C4: Indicador | D4: Peso en el ítem | E4: G1 | F4: G2 | G4: G3 | H4: G4 | I4: G5 | J4: G6 | K4: G7 | L4: G8 | M4: G9 | N4: G10 | O4: G11
A5: P | B5: P1 | C5: Contextualiza el problema en los niveles internacional, nacional y local con fuentes verificables | D5: =Rúbrica!D23 -> 0.25 | E5: 1 | F5: 2 | G5: 2 | H5: 1 | I5: 1 | J5: 2 | K5: 2 | L5: 2 | M5: 1 | N5: 1 | O5: 1
A6: P | B6: P2 | C6: Presenta la magnitud con datos cuantitativos verificables y atribuidos correctamente a la fuente | D6: =Rúbrica!D24 -> 0.25 | E6: 1 | F6: 1 | G6: 1 | H6: 1 | I6: 1 | J6: 1 | K6: 1 | L6: 2 | M6: 0 | N6: 0 | O6: 0
A7: P | B7: P3 | C7: Describe causas y consecuencias, con sustento, y quiénes resultan afectados | D7: =Rúbrica!D25 -> 0.2 | E7: 0 | F7: 1 | G7: 1 | H7: 1 | I7: 1 | J7: 1 | K7: 1 | L7: 2 | M7: 0 | N7: 0 | O7: 0
A8: P | B8: P4 | C8: Delimita el vacío o la brecha de conocimiento que origina el estudio | D8: =Rúbrica!D26 -> 0.15 | E8: 1 | F8: 2 | G8: 2 | H8: 1 | I8: 0 | J8: 2 | K8: 2 | L8: 2 | M8: 1 | N8: 2 | O8: 1
A9: P | B9: P5 | C9: Redacción: claridad, registro académico, coherencia y ausencia de redundancias | D9: =Rúbrica!D27 -> 0.15 | E9: 1 | F9: 1 | G9: 2 | H9: 1 | I9: 1 | J9: 2 | K9: 2 | L9: 2 | M9: 1 | N9: 2 | O9: 1
A10: Q | B10: Q1 | C10: Se formula como interrogante único, claro y abierto, sin respuesta sí/no ni valorativa | D10: =Rúbrica!D28 -> 0.3 | E10: 1 | F10: 1 | G10: 2 | H10: 2 | I10: 2 | J10: 2 | K10: 2 | L10: 2 | M10: 2 | N10: 2 | O10: 2
A11: Q | B11: Q2 | C11: Delimita objeto, población, lugar y tiempo | D11: =Rúbrica!D29 -> 0.3 | E11: 1 | F11: 2 | G11: 2 | H11: 2 | I11: 1 | J11: 2 | K11: 2 | L11: 2 | M11: 2 | N11: 1 | O11: 2
A12: Q | B12: Q3 | C12: Es coherente con el problema planteado (responde al vacío enunciado) | D12: =Rúbrica!D30 -> 0.2 | E12: 1 | F12: 1 | G12: 2 | H12: 2 | I12: 1 | J12: 2 | K12: 2 | L12: 2 | M12: 2 | N12: 2 | O12: 1
A13: Q | B13: Q4 | C13: Es investigable y viable con los recursos y datos disponibles | D13: =Rúbrica!D31 -> 0.2 | E13: 1 | F13: 1 | G13: 2 | H13: 2 | I13: 1 | J13: 2 | K13: 2 | L13: 1 | M13: 1 | N13: 2 | O13: 2
A14: OG | B14: G1 | C14: Verbo en infinitivo, medible, un solo propósito, sin incluir método | D14: =Rúbrica!D32 -> 0.35 | E14: 1 | F14: 2 | G14: 2 | H14: 2 | I14: 2 | J14: 2 | K14: 2 | L14: 1 | M14: 1 | N14: 2 | O14: 2
A15: OG | B15: G2 | C15: Responde a la pregunta problema (misma población, variables y alcance) | D15: =Rúbrica!D33 -> 0.35 | E15: 0 | F15: 2 | G15: 2 | H15: 2 | I15: 2 | J15: 2 | K15: 2 | L15: 2 | M15: 1 | N15: 2 | O15: 2
A16: OG | B16: G3 | C16: Incluye la delimitación (población, contexto, periodo) | D16: =Rúbrica!D34 -> 0.3 | E16: 1 | F16: 2 | G16: 2 | H16: 2 | I16: 2 | J16: 2 | K16: 2 | L16: 2 | M16: 2 | N16: 2 | O16: 2
... A35: T | B35: T4 | C35: Ortografía, estilo, plantilla institucional y declaración de uso de IA | D35: =Rúbrica!D53 -> 0.2 | E35: 0 | F35: 0 | G35: 1 | H35: 1 | I35: 0 | J35: 1 | K35: 1 | L35: 1 | M35: 0 | N35: 1 | O35: 1
A37: Nota por ítem (0 – 5)
A38: Ítem | B38: Código | C38: Nombre | D38: Peso del ítem | E38: G1 | F38: G2 | G38: G3 | H38: G4 | I38: G5 | J38: G6 | K38: G7 | L38: G8 | M38: G9 | N38: G10 | O38: G11
A39: P | B39: P | C39: Descripción del problema | D39: =Rúbrica!C11 -> 0.18 | E39: =SUMPRODUCT($D$5:$D$9,E$5:E$9)/2*Rúbrica!$D$5 -> 2 | F39: =SUMPRODUCT($D$5:$D$9,F$5:F$9)/2*Rúbrica!$D$5 -> 3.5 | G39: =SUMPRODUCT($D$5:$D$9,G$5:G$9)/2*Rúbrica!$D$5 -> 3.875 | H39: =SUMPRODUCT($D$5:$D$9,H$5:H$9)/2*Rúbrica!$D$5 -> 2.5 | I39: =SUMPRODUCT($D$5:$D$9,I$5:I$9)/2*Rúbrica!$D$5 -> 2.125 | J39: =SUMPRODUCT($D$5:$D$9,J$5:J$9)/2*Rúbrica!$D$5 -> 3.875 | K39: =SUMPRODUCT($D$5:$D$9,K$5:K$9)/2*Rúbrica!$D$5 -> 3.875 | L39: =SUMPRODUCT($D$5:$D$9,L$5:L$9)/2*Rúbrica!$D$5 -> 5 | ... O39: =SUMPRODUCT($D$5:$D$9,O$5:O$9)/2*Rúbrica!$D$5 -> 1.375
A40: Q | B40: Q | C40: Pregunta problema | D40: =Rúbrica!C12 -> 0.14 | E40: =SUMPRODUCT($D$10:$D$13,E$10:E$13)/2*Rúbrica!$D$5 -> 2.5 | F40: =SUMPRODUCT($D$10:$D$13,F$10:F$13)/2*Rúbrica!$D$5 -> 3.25 | G40: =SUMPRODUCT($D$10:$D$13,G$10:G$13)/2*Rúbrica!$D$5 -> 5 | H40: =SUMPRODUCT($D$10:$D$13,H$10:H$13)/2*Rúbrica!$D$5 -> 5 | I40: =SUMPRODUCT($D$10:$D$13,I$10:I$13)/2*Rúbrica!$D$5 -> 3.25 | J40: =SUMPRODUCT($D$10:$D$13,J$10:J$13)/2*Rúbrica!$D$5 -> 5 | K40: =SUMPRODUCT($D$10:$D$13,K$10:K$13)/2*Rúbrica!$D$5 -> 5 | L40: =SUMPRODUCT($D$10:$D$13,L$10:L$13)/2*Rúbrica!$D$5 -> 4.5 | ... O40: =SUMPRODUCT($D$10:$D$13,O$10:O$13)/2*Rúbrica!$D$5 -> 4.5
A41: OG | B41: OG | C41: Objetivo general | D41: =Rúbrica!C13 -> 0.09 | E41: =SUMPRODUCT($D$14:$D$16,E$14:E$16)/2*Rúbrica!$D$5 -> 1.625 | F41: =SUMPRODUCT($D$14:$D$16,F$14:F$16)/2*Rúbrica!$D$5 -> 5 | G41: =SUMPRODUCT($D$14:$D$16,G$14:G$16)/2*Rúbrica!$D$5 -> 5 | H41: =SUMPRODUCT($D$14:$D$16,H$14:H$16)/2*Rúbrica!$D$5 -> 5 | I41: =SUMPRODUCT($D$14:$D$16,I$14:I$16)/2*Rúbrica!$D$5 -> 5 | J41: =SUMPRODUCT($D$14:$D$16,J$14:J$16)/2*Rúbrica!$D$5 -> 5 | K41: =SUMPRODUCT($D$14:$D$16,K$14:K$16)/2*Rúbrica!$D$5 -> 5 | L41: =SUMPRODUCT($D$14:$D$16,L$14:L$16)/2*Rúbrica!$D$5 -> 4.125 | ... O41: =SUMPRODUCT($D$14:$D$16,O$14:O$16)/2*Rúbrica!$D$5 -> 5
A42: OE | B42: OE | C42: Objetivos específicos | D42: =Rúbrica!C14 -> 0.09 | E42: =SUMPRODUCT($D$17:$D$19,E$17:E$19)/2*Rúbrica!$D$5 -> 3.375 | F42: =SUMPRODUCT($D$17:$D$19,F$17:F$19)/2*Rúbrica!$D$5 -> 1.625 | G42: =SUMPRODUCT($D$17:$D$19,G$17:G$19)/2*Rúbrica!$D$5 -> 3.375 | H42: =SUMPRODUCT($D$17:$D$19,H$17:H$19)/2*Rúbrica!$D$5 -> 3.25 | I42: =SUMPRODUCT($D$17:$D$19,I$17:I$19)/2*Rúbrica!$D$5 -> 2.5 | J42: =SUMPRODUCT($D$17:$D$19,J$17:J$19)/2*Rúbrica!$D$5 -> 3.375 | K42: =SUMPRODUCT($D$17:$D$19,K$17:K$19)/2*Rúbrica!$D$5 -> 5 | L42: =SUMPRODUCT($D$17:$D$19,L$17:L$19)/2*Rúbrica!$D$5 -> 3.25 | ... O42: =SUMPRODUCT($D$17:$D$19,O$17:O$19)/2*Rúbrica!$D$5 -> 3.375
A43: J | B43: J | C43: Justificación | D43: =Rúbrica!C15 -> 0.13 | E43: =SUMPRODUCT($D$20:$D$23,E$20:E$23)/2*Rúbrica!$D$5 -> 1.875 | F43: =SUMPRODUCT($D$20:$D$23,F$20:F$23)/2*Rúbrica!$D$5 -> 2.5 | G43: =SUMPRODUCT($D$20:$D$23,G$20:G$23)/2*Rúbrica!$D$5 -> 4.375 | H43: =SUMPRODUCT($D$20:$D$23,H$20:H$23)/2*Rúbrica!$D$5 -> 3.125 | I43: =SUMPRODUCT($D$20:$D$23,I$20:I$23)/2*Rúbrica!$D$5 -> 1.875 | J43: =SUMPRODUCT($D$20:$D$23,J$20:J$23)/2*Rúbrica!$D$5 -> 2.5 | K43: =SUMPRODUCT($D$20:$D$23,K$20:K$23)/2*Rúbrica!$D$5 -> 4.375 | L43: =SUMPRODUCT($D$20:$D$23,L$20:L$23)/2*Rúbrica!$D$5 -> 5 | ... O43: =SUMPRODUCT($D$20:$D$23,O$20:O$23)/2*Rúbrica!$D$5 -> 3.125
A44: A | B44: A | C44: Antecedentes (Capítulo 2) | D44: =Rúbrica!C16 -> 0.14 | E44: =SUMPRODUCT($D$24:$D$27,E$24:E$27)/2*Rúbrica!$D$5 -> 3.125 | F44: =SUMPRODUCT($D$24:$D$27,F$24:F$27)/2*Rúbrica!$D$5 -> 3.625 | G44: =SUMPRODUCT($D$24:$D$27,G$24:G$27)/2*Rúbrica!$D$5 -> 4.25 | H44: =SUMPRODUCT($D$24:$D$27,H$24:H$27)/2*Rúbrica!$D$5 -> 3.875 | I44: =SUMPRODUCT($D$24:$D$27,I$24:I$27)/2*Rúbrica!$D$5 -> 1.75 | J44: =SUMPRODUCT($D$24:$D$27,J$24:J$27)/2*Rúbrica!$D$5 -> 4.625 | K44: =SUMPRODUCT($D$24:$D$27,K$24:K$27)/2*Rúbrica!$D$5 -> 4.625 | L44: =SUMPRODUCT($D$24:$D$27,L$24:L$27)/2*Rúbrica!$D$5 -> 3.875 | ... O44: =SUMPRODUCT($D$24:$D$27,O$24:O$27)/2*Rúbrica!$D$5 -> 3.875
A45: M | B45: M | C45: Marco teórico y conceptual (Capítulo 2) | D45: =Rúbrica!C17 -> 0.13 | E45: =SUMPRODUCT($D$28:$D$31,E$28:E$31)/2*Rúbrica!$D$5 -> 3 | F45: =SUMPRODUCT($D$28:$D$31,F$28:F$31)/2*Rúbrica!$D$5 -> 2.5 | G45: =SUMPRODUCT($D$28:$D$31,G$28:G$31)/2*Rúbrica!$D$5 -> 1.875 | H45: =SUMPRODUCT($D$28:$D$31,H$28:H$31)/2*Rúbrica!$D$5 -> 3.875 | I45: =SUMPRODUCT($D$28:$D$31,I$28:I$31)/2*Rúbrica!$D$5 -> 0.625 | J45: =SUMPRODUCT($D$28:$D$31,J$28:J$31)/2*Rúbrica!$D$5 -> 5 | K45: =SUMPRODUCT($D$28:$D$31,K$28:K$31)/2*Rúbrica!$D$5 -> 4.375 | L45: =SUMPRODUCT($D$28:$D$31,L$28:L$31)/2*Rúbrica!$D$5 -> 5 | ... O45: =SUMPRODUCT($D$28:$D$31,O$28:O$31)/2*Rúbrica!$D$5 -> 4.5
A46: T | B46: T | C46: APA 7 y redacción (transversal) | D46: =Rúbrica!C18 -> 0.1 | E46: =SUMPRODUCT($D$32:$D$35,E$32:E$35)/2*Rúbrica!$D$5 -> 1.25 | F46: =SUMPRODUCT($D$32:$D$35,F$32:F$35)/2*Rúbrica!$D$5 -> 2 | G46: =SUMPRODUCT($D$32:$D$35,G$32:G$35)/2*Rúbrica!$D$5 -> 1.125 | H46: =SUMPRODUCT($D$32:$D$35,H$32:H$35)/2*Rúbrica!$D$5 -> 2.5 | I46: =SUMPRODUCT($D$32:$D$35,I$32:I$35)/2*Rúbrica!$D$5 -> 0.625 | J46: =SUMPRODUCT($D$32:$D$35,J$32:J$35)/2*Rúbrica!$D$5 -> 4.5 | K46: =SUMPRODUCT($D$32:$D$35,K$32:K$35)/2*Rúbrica!$D$5 -> 3.125 | L46: =SUMPRODUCT($D$32:$D$35,L$32:L$35)/2*Rúbrica!$D$5 -> 3.25 | ... O46: =SUMPRODUCT($D$32:$D$35,O$32:O$35)/2*Rúbrica!$D$5 -> 3.75
A47: Total | C47: Nota total (0 – 5) | D47: =SUM(D39:D46) -> 1 | E47: =SUMPRODUCT($D$39:$D$46,E39:E46) -> 2.35625 | F47: =SUMPRODUCT($D$39:$D$46,F39:F46) -> 3.03875 | G47: =SUMPRODUCT($D$39:$D$46,G39:G46) -> 3.67125 | H47: =SUMPRODUCT($D$39:$D$46,H39:H46) -> 3.595 | I47: =SUMPRODUCT($D$39:$D$46,I39:I46) -> 2.145 | J47: =SUMPRODUCT($D$39:$D$46,J39:J46) -> 4.22375 | K47: =SUMPRODUCT($D$39:$D$46,K39:K46) -> 4.395 | L47: =SUMPRODUCT($D$39:$D$46,L39:L46) -> 4.36125 | ... O47: =SUMPRODUCT($D$39:$D$46,O39:O46) -> 3.54
C48: Nivel de desempeño | E48: =IF(E47>=Rúbrica!$D$7,"Alto",IF(E47>=Rúbrica!$D$6,"Satisfactorio",IF(E47>=Rúbrica!$D$8,"En desarrollo","Insuficiente"))) -> En desarrollo | F48: =IF(F47>=Rúbrica!$D$7,"Alto",IF(F47>=Rúbrica!$D$6,"Satisfactorio",IF(F47>=Rúbrica!$D$8,"En desarrollo","Insuficiente"))) -> Satisfactorio | G48: =IF(G47>=Rúbrica!$D$7,"Alto",IF(G47>=Rúbrica!$D$6,"Satisfactorio",IF(G47>=Rúbrica!$D$8,"En desarrollo","Insuficiente"))) -> Satisfactorio | H48: =IF(H47>=Rúbrica!$D$7,"Alto",IF(H47>=Rúbrica!$D$6,"Satisfactorio",IF(H47>=Rúbrica!$D$8,"En desarrollo","Insuficiente"))) -> Satisfactorio | I48: =IF(I47>=Rúbrica!$D$7,"Alto",IF(I47>=Rúbrica!$D$6,"Satisfactorio",IF(I47>=Rúbrica!$D$8,"En desarrollo","Insuficiente"))) -> En desarrollo | J48: =IF(J47>=Rúbrica!$D$7,"Alto",IF(J47>=Rúbrica!$D$6,"Satisfactorio",IF(J47>=Rúbrica!$D$8,"En desarrollo","Insuficiente"))) -> Alto | K48: =IF(K47>=Rúbrica!$D$7,"Alto",IF(K47>=Rúbrica!$D$6,"Satisfactorio",IF(K47>=Rúbrica!$D$8,"En desarrollo","Insuficiente"))) -> Alto | L48: =IF(L47>=Rúbrica!$D$7,"Alto",IF(L47>=Rúbrica!$D$6,"Satisfactorio",IF(L47>=Rúbrica!$D$8,"En desarrollo","Insuficiente"))) -> Alto | ... O48: =IF(O47>=Rúbrica!$D$7,"Alto",IF(O47>=Rúbrica!$D$6,"Satisfactorio",IF(O47>=Rúbrica!$D$8,"En desarrollo","Insuficiente"))) -> Satisfactorio
C49: ¿Alcanza el umbral de logro? | E49: =IF(E47>=Rúbrica!$D$6,"Sí","No") -> No | F49: =IF(F47>=Rúbrica!$D$6,"Sí","No") -> Sí | G49: =IF(G47>=Rúbrica!$D$6,"Sí","No") -> Sí | H49: =IF(H47>=Rúbrica!$D$6,"Sí","No") -> Sí | I49: =IF(I47>=Rúbrica!$D$6,"Sí","No") -> No | J49: =IF(J47>=Rúbrica!$D$6,"Sí","No") -> Sí | K49: =IF(K47>=Rúbrica!$D$6,"Sí","No") -> Sí | L49: =IF(L47>=Rúbrica!$D$6,"Sí","No") -> Sí | ... O49: =IF(O47>=Rúbrica!$D$6,"Sí","No") -> Sí
C50: Indicadores con código 0 (de 31) | E50: =COUNTIF(E5:E35,0) -> 6 | F50: =COUNTIF(F5:F35,0) -> 3 | G50: =COUNTIF(G5:G35,0) -> 3 | H50: =COUNTIF(H5:H35,0) -> 0 | I50: =COUNTIF(I5:I35,0) -> 9 | J50: =COUNTIF(J5:J35,0) -> 0 | K50: =COUNTIF(K5:K35,0) -> 0 | L50: =COUNTIF(L5:L35,0) -> 0 | ... O50: =COUNTIF(O5:O35,0) -> 3
C51: Indicadores con código 2 (de 31) | E51: =COUNTIF(E5:E35,2) -> 4 | F51: =COUNTIF(F5:F35,2) -> 9 | G51: =COUNTIF(G5:G35,2) -> 17 | H51: =COUNTIF(H5:H35,2) -> 13 | I51: =COUNTIF(I5:I35,2) -> 4 | J51: =COUNTIF(J5:J35,2) -> 21 | K51: =COUNTIF(K5:K35,2) -> 23 | L51: =COUNTIF(L5:L35,2) -> 22 | ... O51: =COUNTIF(O5:O35,2) -> 16

Sheet Análisis cuantitativo
A1: Análisis cuantitativo
A2: Todas las cifras se calculan con fórmulas a partir de la hoja Calificación. Escala 0 – 5; el umbral de logro es el definido en la hoja Rúbrica.
A3: A. Notas por ítem y total por grupo
A4: Grupo | B4: Tema | C4: P | D4: Q | E4: OG | F4: OE | G4: J | H4: A | I4: M | J4: T | K4: Total | L4: Posición | M4: Nivel | N4: ¿Alcanza umbral?
A5: G1 | B5: Percepción de género en periodismo deportivo | C5: =Calificación!E39 -> 2 | D5: =Calificación!E40 -> 2.5 | E5: =Calificación!E41 -> 1.625 | F5: =Calificación!E42 -> 3.375 | G5: =Calificación!E43 -> 1.875 | H5: =Calificación!E44 -> 3.125 | I5: =Calificación!E45 -> 3 | J5: =Calificación!E46 -> 1.25 | K5: =Calificación!E47 -> 2.35625 | L5: =RANK(K5,$K$5:$K$15,0) -> 10 | M5: =Calificación!E48 -> En desarrollo | N5: =Calificación!E49 -> No
A6: G2 | B6: Administración deportiva en escuelas de fútbol | C6: =Calificación!F39 -> 3.5 | D6: =Calificación!F40 -> 3.25 | E6: =Calificación!F41 -> 5 | F6: =Calificación!F42 -> 1.625 | G6: =Calificación!F43 -> 2.5 | H6: =Calificación!F44 -> 3.625 | I6: =Calificación!F45 -> 2.5 | J6: =Calificación!F46 -> 2 | K6: =Calificación!F47 -> 3.03875 | L6: =RANK(K6,$K$5:$K$15,0) -> 8 | M6: =Calificación!F48 -> Satisfactorio | N6: =Calificación!F49 -> Sí
A7: G3 | B7: Marketing deportivo y sostenibilidad (Patio Bonito) | C7: =Calificación!G39 -> 3.875 | D7: =Calificación!G40 -> 5 | E7: =Calificación!G41 -> 5 | F7: =Calificación!G42 -> 3.375 | G7: =Calificación!G43 -> 4.375 | H7: =Calificación!G44 -> 4.25 | I7: =Calificación!G45 -> 1.875 | J7: =Calificación!G46 -> 1.125 | K7: =Calificación!G47 -> 3.67125 | L7: =RANK(K7,$K$5:$K$15,0) -> 4 | M7: =Calificación!G48 -> Satisfactorio | N7: =Calificación!G49 -> Sí
A8: G4 | B8: Barreras logísticas en torneo de microfútbol | C8: =Calificación!H39 -> 2.5 | D8: =Calificación!H40 -> 5 | E8: =Calificación!H41 -> 5 | F8: =Calificación!H42 -> 3.25 | G8: =Calificación!H43 -> 3.125 | H8: =Calificación!H44 -> 3.875 | I8: =Calificación!H45 -> 3.875 | J8: =Calificación!H46 -> 2.5 | K8: =Calificación!H47 -> 3.595 | L8: =RANK(K8,$K$5:$K$15,0) -> 5 | M8: =Calificación!H48 -> Satisfactorio | N8: =Calificación!H49 -> Sí
A9: G5 | B9: Marketing deportivo y fútbol femenino (visibilidad) | C9: =Calificación!I39 -> 2.125 | D9: =Calificación!I40 -> 3.25 | E9: =Calificación!I41 -> 5 | F9: =Calificación!I42 -> 2.5 | G9: =Calificación!I43 -> 1.875 | H9: =Calificación!I44 -> 1.75 | I9: =Calificación!I45 -> 0.625 | J9: =Calificación!I46 -> 0.625 | K9: =Calificación!I47 -> 2.145 | L9: =RANK(K9,$K$5:$K$15,0) -> 11 | M9: =Calificación!I48 -> En desarrollo | N9: =Calificación!I49 -> No
A10: G6 | B10: Calidad del servicio del gimnasio e intención de continuar | C10: =Calificación!J39 -> 3.875 | D10: =Calificación!J40 -> 5 | E10: =Calificación!J41 -> 5 | F10: =Calificación!J42 -> 3.375 | G10: =Calificación!J43 -> 2.5 | H10: =Calificación!J44 -> 4.625 | I10: =Calificación!J45 -> 5 | J10: =Calificación!J46 -> 4.5 | K10: =Calificación!J47 -> 4.22375 | L10: =RANK(K10,$K$5:$K$15,0) -> 3 | M10: =Calificación!J48 -> Alto | N10: =Calificación!J49 -> Sí
A11: G7 | B11: Desigualdad de género en la trayectoria académica | C11: =Calificación!K39 -> 3.875 | D11: =Calificación!K40 -> 5 | E11: =Calificación!K41 -> 5 | F11: =Calificación!K42 -> 5 | G11: =Calificación!K43 -> 4.375 | H11: =Calificación!K44 -> 4.625 | I11: =Calificación!K45 -> 4.375 | J11: =Calificación!K46 -> 3.125 | K11: =Calificación!K47 -> 4.395 | L11: =RANK(K11,$K$5:$K$15,0) -> 1 | M11: =Calificación!K48 -> Alto | N11: =Calificación!K49 -> Sí
A12: G8 | B12: Economía del baloncesto femenino profesional | C12: =Calificación!L39 -> 5 | D12: =Calificación!L40 -> 4.5 | E12: =Calificación!L41 -> 4.125 | F12: =Calificación!L42 -> 3.25 | G12: =Calificación!L43 -> 5 | H12: =Calificación!L44 -> 3.875 | I12: =Calificación!L45 -> 5 | J12: =Calificación!L46 -> 3.25 | K12: =Calificación!L47 -> 4.36125 | L12: =RANK(K12,$K$5:$K$15,0) -> 2 | M12: =Calificación!L48 -> Alto | N12: =Calificación!L49 -> Sí
A13: G9 | B13: Herramientas tecnológicas de análisis táctico | C13: =Calificación!M39 -> 1.375 | D13: =Calificación!M40 -> 4.5 | E13: =Calificación!M41 -> 3.25 | F13: =Calificación!M42 -> 1.75 | G13: =Calificación!M43 -> 1.875 | H13: =Calificación!M44 -> 1.75 | I13: =Calificación!M45 -> 3.125 | J13: =Calificación!M46 -> 1.375 | K13: =Calificación!M47 -> 2.36 | L13: =RANK(K13,$K$5:$K$15,0) -> 9 | M13: =Calificación!M48 -> En desarrollo | N13: =Calificación!M49 -> No
A14: G10 | B14: Realidad virtual y competencias profesionales | C14: =Calificación!N39 -> 2.125 | D14: =Calificación!N40 -> 4.25 | E14: =Calificación!N41 -> 5 | F14: =Calificación!N42 -> 4.25 | G14: =Calificación!N43 -> 3.75 | H14: =Calificación!N44 -> 3.5 | I14: =Calificación!N45 -> 4.5 | J14: =Calificación!N46 -> 1.875 | K14: =Calificación!N47 -> 3.56 | L14: =RANK(K14,$K$5:$K$15,0) -> 6 | M14: =Calificación!N48 -> Satisfactorio | N14: =Calificación!N49 -> Sí
A15: G11 | B15: Instagram, frecuencia, formato y engagement | C15: =Calificación!O39 -> 1.375 | D15: =Calificación!O40 -> 4.5 | E15: =Calificación!O41 -> 5 | F15: =Calificación!O42 -> 3.375 | G15: =Calificación!O43 -> 3.125 | H15: =Calificación!O44 -> 3.875 | I15: =Calificación!O45 -> 4.5 | J15: =Calificación!O46 -> 3.75 | K15: =Calificación!O47 -> 3.54 | L15: =RANK(K15,$K$5:$K$15,0) -> 7 | M15: =Calificación!O48 -> Satisfactorio | N15: =Calificación!O49 -> Sí
A17: B. Estadística descriptiva por ítem (n = 11 grupos)
A18: Código | B18: Ítem | C18: Peso | D18: Media | E18: Mediana | F18: Mínimo | G18: Máximo | H18: Desv. estándar | I18: Grupos ≥ umbral | J18: % de grupos ≥ umbral | K18: Mayor nota | L18: Menor nota
A19: P | B19: Descripción del problema | C19: =Rúbrica!C11 -> 0.18 | D19: =AVERAGE(C$5:C$15) -> 2.875 | E19: =MEDIAN(C$5:C$15) -> 2.5 | F19: =MIN(C$5:C$15) -> 1.375 | G19: =MAX(C$5:C$15) -> 5 | H19: =STDEV(C$5:C$15) -> 1.2015615 | I19: =COUNTIF(C$5:C$15,">="&Rúbrica!$D$6) -> 5 | J19: =I19/COUNT(C$5:C$15) -> 0.45454545 | K19: =INDEX($A$5:$A$15,MATCH(MAX(C$5:C$15),C$5:C$15,0)) -> G8 | L19: =INDEX($A$5:$A$15,MATCH(MIN(C$5:C$15),C$5:C$15,0)) -> G9
A20: Q | B20: Pregunta problema | C20: =Rúbrica!C12 -> 0.14 | D20: =AVERAGE(D$5:D$15) -> 4.25 | E20: =MEDIAN(D$5:D$15) -> 4.5 | F20: =MIN(D$5:D$15) -> 2.5 | G20: =MAX(D$5:D$15) -> 5 | H20: =STDEV(D$5:D$15) -> 0.8660254 | I20: =COUNTIF(D$5:D$15,">="&Rúbrica!$D$6) -> 10 | J20: =I20/COUNT(D$5:D$15) -> 0.90909091 | K20: =INDEX($A$5:$A$15,MATCH(MAX(D$5:D$15),D$5:D$15,0)) -> G3 | L20: =INDEX($A$5:$A$15,MATCH(MIN(D$5:D$15),D$5:D$15,0)) -> G1
A21: OG | B21: Objetivo general | C21: =Rúbrica!C13 -> 0.09 | D21: =AVERAGE(E$5:E$15) -> 4.4545455 | E21: =MEDIAN(E$5:E$15) -> 5 | F21: =MIN(E$5:E$15) -> 1.625 | G21: =MAX(E$5:E$15) -> 5 | H21: =STDEV(E$5:E$15) -> 1.0929786 | I21: =COUNTIF(E$5:E$15,">="&Rúbrica!$D$6) -> 10 | J21: =I21/COUNT(E$5:E$15) -> 0.90909091 | K21: =INDEX($A$5:$A$15,MATCH(MAX(E$5:E$15),E$5:E$15,0)) -> G2 | L21: =INDEX($A$5:$A$15,MATCH(MIN(E$5:E$15),E$5:E$15,0)) -> G1
A22: OE | B22: Objetivos específicos | C22: =Rúbrica!C14 -> 0.09 | D22: =AVERAGE(F$5:F$15) -> 3.1931818 | E22: =MEDIAN(F$5:F$15) -> 3.375 | F22: =MIN(F$5:F$15) -> 1.625 | G22: =MAX(F$5:F$15) -> 5 | H22: =STDEV(F$5:F$15) -> 0.97686302 | I22: =COUNTIF(F$5:F$15,">="&Rúbrica!$D$6) -> 8 | J22: =I22/COUNT(F$5:F$15) -> 0.72727273 | K22: =INDEX($A$5:$A$15,MATCH(MAX(F$5:F$15),F$5:F$15,0)) -> G7 | L22: =INDEX($A$5:$A$15,MATCH(MIN(F$5:F$15),F$5:F$15,0)) -> G2
A23: J | B23: Justificación | C23: =Rúbrica!C15 -> 0.13 | D23: =AVERAGE(G$5:G$15) -> 3.125 | E23: =MEDIAN(G$5:G$15) -> 3.125 | F23: =MIN(G$5:G$15) -> 1.875 | G23: =MAX(G$5:G$15) -> 5 | H23: =STDEV(G$5:G$15) -> 1.118034 | I23: =COUNTIF(G$5:G$15,">="&Rúbrica!$D$6) -> 6 | J23: =I23/COUNT(G$5:G$15) -> 0.54545455 | K23: =INDEX($A$5:$A$15,MATCH(MAX(G$5:G$15),G$5:G$15,0)) -> G8 | L23: =INDEX($A$5:$A$15,MATCH(MIN(G$5:G$15),G$5:G$15,0)) -> G1
A24: A | B24: Antecedentes (Capítulo 2) | C24: =Rúbrica!C16 -> 0.14 | D24: =AVERAGE(H$5:H$15) -> 3.5340909 | E24: =MEDIAN(H$5:H$15) -> 3.875 | F24: =MIN(H$5:H$15) -> 1.75 | G24: =MAX(H$5:H$15) -> 4.625 | H24: =STDEV(H$5:H$15) -> 0.98914564 | I24: =COUNTIF(H$5:H$15,">="&Rúbrica!$D$6) -> 9 | J24: =I24/COUNT(H$5:H$15) -> 0.81818182 | K24: =INDEX($A$5:$A$15,MATCH(MAX(H$5:H$15),H$5:H$15,0)) -> G6 | L24: =INDEX($A$5:$A$15,MATCH(MIN(H$5:H$15),H$5:H$15,0)) -> G5
A25: M | B25: Marco teórico y conceptual (Capítulo 2) | C25: =Rúbrica!C17 -> 0.13 | D25: =AVERAGE(I$5:I$15) -> 3.4886364 | E25: =MEDIAN(I$5:I$15) -> 3.875 | F25: =MIN(I$5:I$15) -> 0.625 | G25: =MAX(I$5:I$15) -> 5 | H25: =STDEV(I$5:I$15) -> 1.4036276 | I25: =COUNTIF(I$5:I$15,">="&Rúbrica!$D$6) -> 8 | J25: =I25/COUNT(I$5:I$15) -> 0.72727273 | K25: =INDEX($A$5:$A$15,MATCH(MAX(I$5:I$15),I$5:I$15,0)) -> G6 | L25: =INDEX($A$5:$A$15,MATCH(MIN(I$5:I$15),I$5:I$15,0)) -> G5
A26: T | B26: APA 7 y redacción (transversal) | C26: =Rúbrica!C18 -> 0.1 | D26: =AVERAGE(J$5:J$15) -> 2.3068182 | E26: =MEDIAN(J$5:J$15) -> 2 | F26: =MIN(J$5:J$15) -> 0.625 | G26: =MAX(J$5:J$15) -> 4.5 | H26: =STDEV(J$5:J$15) -> 1.2239327 | I26: =COUNTIF(J$5:J$15,">="&Rúbrica!$D$6) -> 4 | J26: =I26/COUNT(J$5:J$15) -> 0.36363636 | K26: =INDEX($A$5:$A$15,MATCH(MAX(J$5:J$15),J$5:J$15,0)) -> G6 | L26: =INDEX($A$5:$A$15,MATCH(MIN(J$5:J$15),J$5:J$15,0)) -> G5
A27: Total | B27: Nota total | C27: =SUM(C19:C26) -> 1 | D27: =AVERAGE(K$5:K$15) -> 3.3860227 | E27: =MEDIAN(K$5:K$15) -> 3.56 | F27: =MIN(K$5:K$15) -> 2.145 | G27: =MAX(K$5:K$15) -> 4.395 | H27: =STDEV(K$5:K$15) -> 0.81386632 | I27: =COUNTIF(K$5:K$15,">="&Rúbrica!$D$6) -> 8 | J27: =I27/COUNT(K$5:K$15) -> 0.72727273 | K27: =INDEX($A$5:$A$15,MATCH(MAX(K$5:K$15),K$5:K$15,0)) -> G7 | L27: =INDEX($A$5:$A$15,MATCH(MIN(K$5:K$15),K$5:K$15,0)) -> G5
A30: C. Cumplimiento por indicador (n = 11 grupos)
A31: Código | B31: Indicador | C31: Grupos con 2 | D31: Grupos con 1 | E31: Grupos con 0 | F31: % con cumplimiento pleno | G31: % con código 0 | H31: Media (0 – 2) | I31: Prioridad de mejora
A32: P1 | B32: Contextualiza el problema en los niveles internacional, nacional y local con fuentes verificables | C32: =COUNTIF(Calificación!$E$5:$O$5,2) -> 5 | D32: =COUNTIF(Calificación!$E$5:$O$5,1) -> 6 | E32: =COUNTIF(Calificación!$E$5:$O$5,0) -> 0 | F32: =C32/COUNT(Calificación!$E$5:$O$5) -> 0.45454545 | G32: =E32/COUNT(Calificación!$E$5:$O$5) -> 0 | H32: =AVERAGE(Calificación!$E$5:$O$5) -> 1.4545455 | I32: =IF(G32>=0.5,"Crítica",IF(G32>=0.25,"Alta",IF(G32>0,"Media","Sin casos con 0"))) -> Sin casos con 0
A33: P2 | B33: Presenta la magnitud con datos cuantitativos verificables y atribuidos correctamente a la fuente | C33: =COUNTIF(Calificación!$E$6:$O$6,2) -> 1 | D33: =COUNTIF(Calificación!$E$6:$O$6,1) -> 7 | E33: =COUNTIF(Calificación!$E$6:$O$6,0) -> 3 | F33: =C33/COUNT(Calificación!$E$6:$O$6) -> 0.090909091 | G33: =E33/COUNT(Calificación!$E$6:$O$6) -> 0.27272727 | H33: =AVERAGE(Calificación!$E$6:$O$6) -> 0.81818182 | I33: =IF(G33>=0.5,"Crítica",IF(G33>=0.25,"Alta",IF(G33>0,"Media","Sin casos con 0"))) -> Alta
A34: P3 | B34: Describe causas y consecuencias, con sustento, y quiénes resultan afectados | C34: =COUNTIF(Calificación!$E$7:$O$7,2) -> 1 | D34: =COUNTIF(Calificación!$E$7:$O$7,1) -> 6 | E34: =COUNTIF(Calificación!$E$7:$O$7,0) -> 4 | F34: =C34/COUNT(Calificación!$E$7:$O$7) -> 0.090909091 | G34: =E34/COUNT(Calificación!$E$7:$O$7) -> 0.36363636 | H34: =AVERAGE(Calificación!$E$7:$O$7) -> 0.72727273 | I34: =IF(G34>=0.5,"Crítica",IF(G34>=0.25,"Alta",IF(G34>0,"Media","Sin casos con 0"))) -> Alta
A35: P4 | B35: Delimita el vacío o la brecha de conocimiento que origina el estudio | C35: =COUNTIF(Calificación!$E$8:$O$8,2) -> 6 | D35: =COUNTIF(Calificación!$E$8:$O$8,1) -> 4 | E35: =COUNTIF(Calificación!$E$8:$O$8,0) -> 1 | F35: =C35/COUNT(Calificación!$E$8:$O$8) -> 0.54545455 | G35: =E35/COUNT(Calificación!$E$8:$O$8) -> 0.090909091 | H35: =AVERAGE(Calificación!$E$8:$O$8) -> 1.4545455 | I35: =IF(G35>=0.5,"Crítica",IF(G35>=0.25,"Alta",IF(G35>0,"Media","Sin casos con 0"))) -> Media
A36: P5 | B36: Redacción: claridad, registro académico, coherencia y ausencia de redundancias | C36: =COUNTIF(Calificación!$E$9:$O$9,2) -> 5 | D36: =COUNTIF(Calificación!$E$9:$O$9,1) -> 6 | E36: =COUNTIF(Calificación!$E$9:$O$9,0) -> 0 | F36: =C36/COUNT(Calificación!$E$9:$O$9) -> 0.45454545 | G36: =E36/COUNT(Calificación!$E$9:$O$9) -> 0 | H36: =AVERAGE(Calificación!$E$9:$O$9) -> 1.4545455 | I36: =IF(G36>=0.5,"Crítica",IF(G36>=0.25,"Alta",IF(G36>0,"Media","Sin casos con 0"))) -> Sin casos con 0
A37: Q1 | B37: Se formula como interrogante único, claro y abierto, sin respuesta sí/no ni valorativa | C37: =COUNTIF(Calificación!$E$10:$O$10,2) -> 9 | D37: =COUNTIF(Calificación!$E$10:$O$10,1) -> 2 | E37: =COUNTIF(Calificación!$E$10:$O$10,0) -> 0 | F37: =C37/COUNT(Calificación!$E$10:$O$10) -> 0.81818182 | G37: =E37/COUNT(Calificación!$E$10:$O$10) -> 0 | H37: =AVERAGE(Calificación!$E$10:$O$10) -> 1.8181818 | I37: =IF(G37>=0.5,"Crítica",IF(G37>=0.25,"Alta",IF(G37>0,"Media","Sin casos con 0"))) -> Sin casos con 0
A38: Q2 | B38: Delimita objeto, población, lugar y tiempo | C38: =COUNTIF(Calificación!$E$11:$O$11,2) -> 8 | D38: =COUNTIF(Calificación!$E$11:$O$11,1) -> 3 | E38: =COUNTIF(Calificación!$E$11:$O$11,0) -> 0 | F38: =C38/COUNT(Calificación!$E$11:$O$11) -> 0.72727273 | G38: =E38/COUNT(Calificación!$E$11:$O$11) -> 0 | H38: =AVERAGE(Calificación!$E$11:$O$11) -> 1.7272727 | I38: =IF(G38>=0.5,"Crítica",IF(G38>=0.25,"Alta",IF(G38>0,"Media","Sin casos con 0"))) -> Sin casos con 0
A39: Q3 | B39: Es coherente con el problema planteado (responde al vacío enunciado) | C39: =COUNTIF(Calificación!$E$12:$O$12,2) -> 7 | D39: =COUNTIF(Calificación!$E$12:$O$12,1) -> 4 | E39: =COUNTIF(Calificación!$E$12:$O$12,0) -> 0 | F39: =C39/COUNT(Calificación!$E$12:$O$12) -> 0.63636364 | G39: =E39/COUNT(Calificación!$E$12:$O$12) -> 0 | H39: =AVERAGE(Calificación!$E$12:$O$12) -> 1.6363636 | I39: =IF(G39>=0.5,"Crítica",IF(G39>=0.25,"Alta",IF(G39>0,"Media","Sin casos con 0"))) -> Sin casos con 0
A40: Q4 | B40: Es investigable y viable con los recursos y datos disponibles | C40: =COUNTIF(Calificación!$E$13:$O$13,2) -> 6 | D40: =COUNTIF(Calificación!$E$13:$O$13,1) -> 5 | E40: =COUNTIF(Calificación!$E$13:$O$13,0) -> 0 | F40: =C40/COUNT(Calificación!$E$13:$O$13) -> 0.54545455 | G40: =E40/COUNT(Calificación!$E$13:$O$13) -> 0 | H40: =AVERAGE(Calificación!$E$13:$O$13) -> 1.5454545 | I40: =IF(G40>=0.5,"Crítica",IF(G40>=0.25,"Alta",IF(G40>0,"Media","Sin casos con 0"))) -> Sin casos con 0
A41: G1 | B41: Verbo en infinitivo, medible, un solo propósito, sin incluir método | C41: =COUNTIF(Calificación!$E$14:$O$14,2) -> 8 | D41: =COUNTIF(Calificación!$E$14:$O$14,1) -> 3 | E41: =COUNTIF(Calificación!$E$14:$O$14,0) -> 0 | F41: =C41/COUNT(Calificación!$E$14:$O$14) -> 0.72727273 | G41: =E41/COUNT(Calificación!$E$14:$O$14) -> 0 | H41: =AVERAGE(Calificación!$E$14:$O$14) -> 1.7272727 | I41: =IF(G41>=0.5,"Crítica",IF(G41>=0.25,"Alta",IF(G41>0,"Media","Sin casos con 0"))) -> Sin casos con 0
A42: G2 | B42: Responde a la pregunta problema (misma población, variables y alcance) | C42: =COUNTIF(Calificación!$E$15:$O$15,2) -> 9 | D42: =COUNTIF(Calificación!$E$15:$O$15,1) -> 1 | E42: =COUNTIF(Calificación!$E$15:$O$15,0) -> 1 | F42: =C42/COUNT(Calificación!$E$15:$O$15) -> 0.81818182 | G42: =E42/COUNT(Calificación!$E$15:$O$15) -> 0.090909091 | H42: =AVERAGE(Calificación!$E$15:$O$15) -> 1.7272727 | I42: =IF(G42>=0.5,"Crítica",IF(G42>=0.25,"Alta",IF(G42>0,"Media","Sin casos con 0"))) -> Media
A43: G3 | B43: Incluye la delimitación (población, contexto, periodo) | C43: =COUNTIF(Calificación!$E$16:$O$16,2) -> 10 | D43: =COUNTIF(Calificación!$E$16:$O$16,1) -> 1 | E43: =COUNTIF(Calificación!$E$16:$O$16,0) -> 0 | F43: =C43/COUNT(Calificación!$E$16:$O$16) -> 0.90909091 | G43: =E43/COUNT(Calificación!$E$16:$O$16) -> 0 | H43: =AVERAGE(Calificación!$E$16:$O$16) -> 1.9090909 | I43: =IF(G43>=0.5,"Crítica",IF(G43>=0.25,"Alta",IF(G43>0,"Media","Sin casos con 0"))) -> Sin casos con 0
A44: E1 | B44: Verbos en infinitivo y medibles; un resultado de conocimiento por objetivo (no pasos del procedimiento) | C44: =COUNTIF(Calificación!$E$17:$O$17,2) -> 3 | D44: =COUNTIF(Calificación!$E$17:$O$17,1) -> 7 | E44: =COUNTIF(Calificación!$E$17:$O$17,0) -> 1 | F44: =C44/COUNT(Calificación!$E$17:$O$17) -> 0.27272727 | G44: =E44/COUNT(Calificación!$E$17:$O$17) -> 0.090909091 | H44: =AVERAGE(Calificación!$E$17:$O$17) -> 1.1818182 | I44: =IF(G44>=0.5,"Crítica",IF(G44>=0.25,"Alta",IF(G44>0,"Media","Sin casos con 0"))) -> Media
A45: E2 | B45: Derivan del objetivo general y lo cubren sin exceder su alcance | C45: =COUNTIF(Calificación!$E$18:$O$18,2) -> 4 | D45: =COUNTIF(Calificación!$E$18:$O$18,1) -> 7 | E45: =COUNTIF(Calificación!$E$18:$O$18,0) -> 0 | F45: =C45/COUNT(Calificación!$E$18:$O$18) -> 0.36363636 | G45: =E45/COUNT(Calificación!$E$18:$O$18) -> 0 | H45: =AVERAGE(Calificación!$E$18:$O$18) -> 1.3636364 | I45: =IF(G45>=0.5,"Crítica",IF(G45>=0.25,"Alta",IF(G45>0,"Media","Sin casos con 0"))) -> Sin casos con 0
A46: E3 | B46: Secuencia lógica y alcance viable para una monografía | C46: =COUNTIF(Calificación!$E$19:$O$19,2) -> 4 | D46: =COUNTIF(Calificación!$E$19:$O$19,1) -> 6 | E46: =COUNTIF(Calificación!$E$19:$O$19,0) -> 1 | F46: =C46/COUNT(Calificación!$E$19:$O$19) -> 0.36363636 | G46: =E46/COUNT(Calificación!$E$19:$O$19) -> 0.090909091 | H46: =AVERAGE(Calificación!$E$19:$O$19) -> 1.2727273 | I46: =IF(G46>=0.5,"Crítica",IF(G46>=0.25,"Alta",IF(G46>0,"Media","Sin casos con 0"))) -> Media
A47: J1 | B47: Justificación académica o teórica vinculada con el vacío de conocimiento | C47: =COUNTIF(Calificación!$E$20:$O$20,2) -> 5 | D47: =COUNTIF(Calificación!$E$20:$O$20,1) -> 6 | E47: =COUNTIF(Calificación!$E$20:$O$20,0) -> 0 | F47: =C47/COUNT(Calificación!$E$20:$O$20) -> 0.45454545 | G47: =E47/COUNT(Calificación!$E$20:$O$20) -> 0 | H47: =AVERAGE(Calificación!$E$20:$O$20) -> 1.4545455 | I47: =IF(G47>=0.5,"Crítica",IF(G47>=0.25,"Alta",IF(G47>0,"Media","Sin casos con 0"))) -> Sin casos con 0
A48: J2 | B48: Justificación social y práctica para la gestión deportiva, con destinatarios identificados | C48: =COUNTIF(Calificación!$E$21:$O$21,2) -> 7 | D48: =COUNTIF(Calificación!$E$21:$O$21,1) -> 4 | E48: =COUNTIF(Calificación!$E$21:$O$21,0) -> 0 | F48: =C48/COUNT(Calificación!$E$21:$O$21) -> 0.63636364 | G48: =E48/COUNT(Calificación!$E$21:$O$21) -> 0 | H48: =AVERAGE(Calificación!$E$21:$O$21) -> 1.6363636 | I48: =IF(G48>=0.5,"Crítica",IF(G48>=0.25,"Alta",IF(G48>0,"Media","Sin casos con 0"))) -> Sin casos con 0
A49: J3 | B49: Pertinencia y viabilidad del estudio (acceso, tiempo, recursos) | C49: =COUNTIF(Calificación!$E$22:$O$22,2) -> 2 | D49: =COUNTIF(Calificación!$E$22:$O$22,1) -> 6 | E49: =COUNTIF(Calificación!$E$22:$O$22,0) -> 3 | F49: =C49/COUNT(Calificación!$E$22:$O$22) -> 0.18181818 | G49: =E49/COUNT(Calificación!$E$22:$O$22) -> 0.27272727 | H49: =AVERAGE(Calificación!$E$22:$O$22) -> 0.90909091 | I49: =IF(G49>=0.5,"Crítica",IF(G49>=0.25,"Alta",IF(G49>0,"Media","Sin casos con 0"))) -> Alta
A50: J4 | B50: Sustento con fuentes y redacción sin afirmaciones no respaldadas | C50: =COUNTIF(Calificación!$E$23:$O$23,2) -> 3 | D50: =COUNTIF(Calificación!$E$23:$O$23,1) -> 5 | E50: =COUNTIF(Calificación!$E$23:$O$23,0) -> 3 | F50: =C50/COUNT(Calificación!$E$23:$O$23) -> 0.27272727 | G50: =E50/COUNT(Calificación!$E$23:$O$23) -> 0.27272727 | H50: =AVERAGE(Calificación!$E$23:$O$23) -> 1 | I50: =IF(G50>=0.5,"Crítica",IF(G50>=0.25,"Alta",IF(G50>0,"Media","Sin casos con 0"))) -> Alta
A51: A1 | B51: Pertinencia, actualidad y calidad de las fuentes | C51: =COUNTIF(Calificación!$E$24:$O$24,2) -> 3 | D51: =COUNTIF(Calificación!$E$24:$O$24,1) -> 8 | E51: =COUNTIF(Calificación!$E$24:$O$24,0) -> 0 | F51: =C51/COUNT(Calificación!$E$24:$O$24) -> 0.27272727 | G51: =E51/COUNT(Calificación!$E$24:$O$24) -> 0 | H51: =AVERAGE(Calificación!$E$24:$O$24) -> 1.2727273 | I51: =IF(G51>=0.5,"Crítica",IF(G51>=0.25,"Alta",IF(G51>0,"Media","Sin casos con 0"))) -> Sin casos con 0
A52: A2 | B52: Estructura de la reseña: objetivo, método, resultados y aporte al estudio | C52: =COUNTIF(Calificación!$E$25:$O$25,2) -> 8 | D52: =COUNTIF(Calificación!$E$25:$O$25,1) -> 3 | E52: =COUNTIF(Calificación!$E$25:$O$25,0) -> 0 | F52: =C52/COUNT(Calificación!$E$25:$O$25) -> 0.72727273 | G52: =E52/COUNT(Calificación!$E$25:$O$25) -> 0 | H52: =AVERAGE(Calificación!$E$25:$O$25) -> 1.7272727 | I52: =IF(G52>=0.5,"Crítica",IF(G52>=0.25,"Alta",IF(G52>0,"Media","Sin casos con 0"))) -> Sin casos con 0
A53: A3 | B53: Síntesis crítica de los antecedentes y brecha formulada | C53: =COUNTIF(Calificación!$E$26:$O$26,2) -> 7 | D53: =COUNTIF(Calificación!$E$26:$O$26,1) -> 1 | E53: =COUNTIF(Calificación!$E$26:$O$26,0) -> 3 | F53: =C53/COUNT(Calificación!$E$26:$O$26) -> 0.63636364 | G53: =E53/COUNT(Calificación!$E$26:$O$26) -> 0.27272727 | H53: =AVERAGE(Calificación!$E$26:$O$26) -> 1.3636364 | I53: =IF(G53>=0.5,"Crítica",IF(G53>=0.25,"Alta",IF(G53>0,"Media","Sin casos con 0"))) -> Alta
A54: A4 | B54: Cobertura de niveles (internacional, nacional y local) | C54: =COUNTIF(Calificación!$E$27:$O$27,2) -> 3 | D54: =COUNTIF(Calificación!$E$27:$O$27,1) -> 8 | E54: =COUNTIF(Calificación!$E$27:$O$27,0) -> 0 | F54: =C54/COUNT(Calificación!$E$27:$O$27) -> 0.27272727 | G54: =E54/COUNT(Calificación!$E$27:$O$27) -> 0 | H54: =AVERAGE(Calificación!$E$27:$O$27) -> 1.2727273 | I54: =IF(G54>=0.5,"Crítica",IF(G54>=0.25,"Alta",IF(G54>0,"Media","Sin casos con 0"))) -> Sin casos con 0
A55: M1 | B55: Desarrolla las categorías o variables del problema con definiciones | C55: =COUNTIF(Calificación!$E$28:$O$28,2) -> 6 | D55: =COUNTIF(Calificación!$E$28:$O$28,1) -> 4 | E55: =COUNTIF(Calificación!$E$28:$O$28,0) -> 1 | F55: =C55/COUNT(Calificación!$E$28:$O$28) -> 0.54545455 | G55: =E55/COUNT(Calificación!$E$28:$O$28) -> 0.090909091 | H55: =AVERAGE(Calificación!$E$28:$O$28) -> 1.4545455 | I55: =IF(G55>=0.5,"Crítica",IF(G55>=0.25,"Alta",IF(G55>0,"Media","Sin casos con 0"))) -> Media
A56: M2 | B56: Autores y fuentes de base pertinentes (primarias, no solo secundarias) | C56: =COUNTIF(Calificación!$E$29:$O$29,2) -> 5 | D56: =COUNTIF(Calificación!$E$29:$O$29,1) -> 4 | E56: =COUNTIF(Calificación!$E$29:$O$29,0) -> 2 | F56: =C56/COUNT(Calificación!$E$29:$O$29) -> 0.45454545 | G56: =E56/COUNT(Calificación!$E$29:$O$29) -> 0.18181818 | H56: =AVERAGE(Calificación!$E$29:$O$29) -> 1.2727273 | I56: =IF(G56>=0.5,"Crítica",IF(G56>=0.25,"Alta",IF(G56>0,"Media","Sin casos con 0"))) -> Media
A57: M3 | B57: Articulación del marco con la pregunta, los objetivos y el diseño | C57: =COUNTIF(Calificación!$E$30:$O$30,2) -> 6 | D57: =COUNTIF(Calificación!$E$30:$O$30,1) -> 5 | E57: =COUNTIF(Calificación!$E$30:$O$30,0) -> 0 | F57: =C57/COUNT(Calificación!$E$30:$O$30) -> 0.54545455 | G57: =E57/COUNT(Calificación!$E$30:$O$30) -> 0 | H57: =AVERAGE(Calificación!$E$30:$O$30) -> 1.5454545 | I57: =IF(G57>=0.5,"Crítica",IF(G57>=0.25,"Alta",IF(G57>0,"Media","Sin casos con 0"))) -> Sin casos con 0
A58: M4 | B58: Paráfrasis, redacción y cohesión; sin fragmentos sin fuente | C58: =COUNTIF(Calificación!$E$31:$O$31,2) -> 4 | D58: =COUNTIF(Calificación!$E$31:$O$31,1) -> 6 | E58: =COUNTIF(Calificación!$E$31:$O$31,0) -> 1 | F58: =C58/COUNT(Calificación!$E$31:$O$31) -> 0.36363636 | G58: =E58/COUNT(Calificación!$E$31:$O$31) -> 0.090909091 | H58: =AVERAGE(Calificación!$E$31:$O$31) -> 1.2727273 | I58: =IF(G58>=0.5,"Crítica",IF(G58>=0.25,"Alta",IF(G58>0,"Media","Sin casos con 0"))) -> Media
A59: T1 | B59: Citas en texto con formato APA 7 (narrativas y parentéticas, et al., secundarias) | C59: =COUNTIF(Calificación!$E$32:$O$32,2) -> 3 | D59: =COUNTIF(Calificación!$E$32:$O$32,1) -> 8 | E59: =COUNTIF(Calificación!$E$32:$O$32,0) -> 0 | F59: =C59/COUNT(Calificación!$E$32:$O$32) -> 0.27272727 | G59: =E59/COUNT(Calificación!$E$32:$O$32) -> 0 | H59: =AVERAGE(Calificación!$E$32:$O$32) -> 1.2727273 | I59: =IF(G59>=0.5,"Crítica",IF(G59>=0.25,"Alta",IF(G59>0,"Media","Sin casos con 0"))) -> Sin casos con 0
A60: T2 | B60: Correspondencia entre citas y lista de referencias (sin huérfanas ni faltantes) | C60: =COUNTIF(Calificación!$E$33:$O$33,2) -> 2 | D60: =COUNTIF(Calificación!$E$33:$O$33,1) -> 6 | E60: =COUNTIF(Calificación!$E$33:$O$33,0) -> 3 | F60: =C60/COUNT(Calificación!$E$33:$O$33) -> 0.18181818 | G60: =E60/COUNT(Calificación!$E$33:$O$33) -> 0.27272727 | H60: =AVERAGE(Calificación!$E$33:$O$33) -> 0.90909091 | I60: =IF(G60>=0.5,"Crítica",IF(G60>=0.25,"Alta",IF(G60>0,"Media","Sin casos con 0"))) -> Alta
A61: T3 | B61: Lista de referencias en formato APA 7 (autor, orden, DOI/URL, sin duplicados) | C61: =COUNTIF(Calificación!$E$34:$O$34,2) -> 2 | D61: =COUNTIF(Calificación!$E$34:$O$34,1) -> 5 | E61: =COUNTIF(Calificación!$E$34:$O$34,0) -> 4 | F61: =C61/COUNT(Calificación!$E$34:$O$34) -> 0.18181818 | G61: =E61/COUNT(Calificación!$E$34:$O$34) -> 0.36363636 | H61: =AVERAGE(Calificación!$E$34:$O$34) -> 0.81818182 | I61: =IF(G61>=0.5,"Crítica",IF(G61>=0.25,"Alta",IF(G61>0,"Media","Sin casos con 0"))) -> Alta
A62: T4 | B62: Ortografía, estilo, plantilla institucional y declaración de uso de IA | C62: =COUNTIF(Calificación!$E$35:$O$35,2) -> 0 | D62: =COUNTIF(Calificación!$E$35:$O$35,1) -> 7 | E62: =COUNTIF(Calificación!$E$35:$O$35,0) -> 4 | F62: =C62/COUNT(Calificación!$E$35:$O$35) -> 0 | G62: =E62/COUNT(Calificación!$E$35:$O$35) -> 0.36363636 | H62: =AVERAGE(Calificación!$E$35:$O$35) -> 0.63636364 | I62: =IF(G62>=0.5,"Crítica",IF(G62>=0.25,"Alta",IF(G62>0,"Media","Sin casos con 0"))) -> Alta
A65: D. Distribución por nivel de desempeño
A66: Nivel | B66: Criterio | C66: Grupos | D66: %
A67: Alto | B67: ="Nota ≥ "&TEXT(Rúbrica!$D$7,"0.0") -> Nota ≥ 4.0 | C67: =COUNTIF($M$5:$M$15,A67) -> 3 | D67: =C67/COUNTA($M$5:$M$15) -> 0.27272727
A68: Satisfactorio | B68: ="Nota ≥ "&TEXT(Rúbrica!$D$6,"0.0")&" y < "&TEXT(Rúbrica!$D$7,"0.0") -> Nota ≥ 3.0 y < 4.0 | C68: =COUNTIF($M$5:$M$15,A68) -> 5 | D68: =C68/COUNTA($M$5:$M$15) -> 0.45454545
A69: En desarrollo | B69: ="Nota ≥ "&TEXT(Rúbrica!$D$8,"0.0")&" y < "&TEXT(Rúbrica!$D$6,"0.0") -> Nota ≥ 2.0 y < 3.0 | C69: =COUNTIF($M$5:$M$15,A69) -> 3 | D69: =C69/COUNTA($M$5:$M$15) -> 0.27272727
A70: Insuficiente | B70: ="Nota < "&TEXT(Rúbrica!$D$8,"0.0") -> Nota < 2.0 | C70: =COUNTIF($M$5:$M$15,A70) -> 0 | D70: =C70/COUNTA($M$5:$M$15) -> 0
A71: Total | C71: =SUM(C67:C70) -> 11 | D71: =SUM(D67:D70) -> 1

Sheet Análisis cualitativo
A1: Análisis cualitativo por grupo e ítem
A2: Errores de elaboración identificados, con ejemplos tomados de los documentos. La nota de cada ítem se enlaza con la hoja Calificación.
A4: Grupo | B4: Ítem | C4: Nota del ítem (0 – 5) | D4: Condición | E4: Hallazgos y errores de elaboración (con ejemplos)
A5: G1 | B5: Descripción del problema | C5: =Calificación!E39 -> 2 | D5: =IF(C5>=Rúbrica!$D$6,"Logrado","No logrado") -> No logrado | E5: Contextualiza con un dato internacional (Boczek et al., 2023: 91,7 % de artículos firmados por hombres) y un antecedente nacional cualitativo (Zapata Correa et al., 2026), pero no aporta cifras colombianas ni locales (Bogotá). No se describen causas ni consecuencias de la desigualdad en el periodismo deportivo, y el vacío se enuncia como desconocimiento de la percepción de una población, no como carencia frente a la literatura. La redacción repite tres veces la salvedad «sin asumir previamente que existe una situación de desigualdad», y el planteamiento se duplica entre la Introducción y la Descripción del problema. El dato de Boczek se reporta como 8,2 % en el problema y como «8,1 %» en antecedentes.
A6: G1 | B6: Pregunta problema | C6: =Calificación!E40 -> 2.5 | D6: =IF(C6>=Rúbrica!$D$6,"Logrado","No logrado") -> No logrado | E6: Formulada como interrogante abierta y con población y periodo (segundo periodo de 2026), pero extensa y con una incisa entre guiones. Integra dos objetos: la percepción de estudiantes y la gestión de comunicaciones institucionales de clubes («como referente para…»), lo que impide delimitar la unidad de análisis. La frase que la antecede («se plantea la siguiente pregunta de investigación») carece de dos puntos.
A7: G1 | B7: Objetivo general | C7: =Calificación!E41 -> 1.625 | D7: =IF(C7>=Rúbrica!$D$6,"Logrado","No logrado") -> No logrado | E7: Verbo en infinitivo, pero «analizar la relación entre» sugiere un propósito relacional que la metodología (descriptivo-interpretativa, cualitativa) no contempla. Contiene error de redacción («relación de entre»). No responde a la pregunta: sustituye la población (estudiantes) por documentos (publicaciones y noticias). Sin delimitación temporal ni de unidades (cuántos clubes, qué medios).
A8: G1 | B8: Objetivos específicos | C8: =Calificación!E42 -> 3.375 | D8: =IF(C8>=Rúbrica!$D$6,"Logrado","No logrado") -> Logrado | E8: Los verbos (identificar, analizar, comparar) son pertinentes y secuenciales, aunque el tercero añade «con el propósito de reconocer posibles relaciones», lo que introduce un segundo propósito. Ninguno aborda las oportunidades profesionales, la visibilidad y la participación que la pregunta menciona. «genero» sin tilde.
A9: G1 | B9: Justificación | C9: =Calificación!E43 -> 1.875 | D9: =IF(C9>=Rúbrica!$D$6,"Logrado","No logrado") -> No logrado | E9: Se articula en cuatro párrafos (social, académico, profesional, delimitación) y reconoce la limitación de no generalizar. Se sustenta únicamente en dos fuentes (Boczek et al., 2023; Zapata Correa et al., 2026) que se repiten del problema. No explicita la contribución a la gestión deportiva (comunicación de clubes), no hay viabilidad (acceso a la población, tiempo, recursos) y la justificación no corresponde al objeto del objetivo general.
A10: G1 | B10: Antecedentes (Capítulo 2) | C10: =Calificación!E44 -> 3.125 | D10: =IF(C10>=Rúbrica!$D$6,"Logrado","No logrado") -> Logrado | E10: Seis estudios reseñados con estructura reconocible (objetivo, método, resultado, pertinencia) y revistas indexadas; 2016 a 2026. Faltan: encabezado y nexo en Boczek et al. (2023), cierre de síntesis, identificación del vacío y antecedentes locales o sobre estudiantes de formación deportiva (Ramon Vegas et al., 2019 está en referencias pero no se usa). Coronel Puello (2024) no figura en la lista de referencias. Afirmaciones sobredimensionadas: un estudio cualitativo con siete periodistas «demuestra la existencia de desigualdades».
A11: G1 | B11: Marco teórico y conceptual (Capítulo 2) | C11: =Calificación!E45 -> 3 | D11: =IF(C11>=Rúbrica!$D$6,"Logrado","No logrado") -> Logrado | E11: Presenta representaciones sociales, framing y perspectiva de género; las fuentes primarias (Moscovici, 1988; Antunovic y Whiteside, 2018) existen, pero Entman (1993) y Jodelet (2008) no están en las referencias y Calvo Ortega y Gutiérrez San Miguel aparece como 2017 en el texto frente a 2016 en la lista. La sección se titula «Marco conceptual» pero desarrolla teorías. No se define igualdad de género, comunicación institucional ni visibilidad, que son las categorías del instrumento. La teoría de base corresponde a la percepción de estudiantes, no al análisis de contenido.
A12: G1 | B12: APA 7 y redacción (transversal) | C12: =Calificación!E46 -> 1.25 | D12: =IF(C12>=Rúbrica!$D$6,"Logrado","No logrado") -> No logrado | E12: Referencias: 14 entradas, 8 sin cita en el texto (Bruce, 2016; Calvo-Ortega, 2020; Gómez-Colell et al., 2017; Olabe Sánchez, 2010 y 2012; Ramon Vegas et al., 2019; Sainz de Baranda Andújar, 2014a y 2014b) y 4 citas sin referencia (Coronel Puello, 2024; Entman, 1993; Jodelet, 2008; Calvo Ortega y Gutiérrez San Miguel, 2017). Cita narrativa con cuatro autores sin «et al.» (Zapata Correa, Durán-Palacio, Rodríguez Gómez y Restrepo Echavarría, 2026). Persisten textos de plantilla en el cuerpo (Dedicatoria (opcional), instrucciones del Resumen, «Figura 1 Título en cursiva», «Indicar la mejor opción…»).
A13: G2 | B13: Descripción del problema | C13: =Calificación!F39 -> 3.5 | D13: =IF(C13>=Rúbrica!$D$6,"Logrado","No logrado") -> Logrado | E13: Estructura por niveles internacional, nacional y local, con datos verificables (Sarmiento Espiau et al., 2025: n = 125; Barahona Vinasco et al., 2023: 103 ligas y clubes; 26,86 % y 41,75 %), síntesis y vacío explícito («hasta donde permitió establecer la búsqueda realizada»). Debilidades: las cifras provienen de Caldas y de Antioquia (2010), no de Bogotá; la deserción de deportistas y la ineficiencia en recursos se afirman en la Introducción sin fuente; la escuela Elizalde FC aparece sin justificar por qué es el caso de estudio. Los párrafos de nivel internacional y nacional se reproducen casi literalmente en Antecedentes. La Introducción tiene fallas graves de redacción («manejas unas de las principales ofertas», «vacíos internacionales», «se en cargan», «En conclusión» al inicio del documento).
A14: G2 | B14: Pregunta problema | C14: =Calificación!F40 -> 3.25 | D14: =IF(C14>=Rúbrica!$D$6,"Logrado","No logrado") -> Logrado | E14: Delimita sujeto, lugar (Kennedy, Bogotá) y periodo (2026-2). Sin embargo, «¿Cómo fortalecer la gestión…?» es una pregunta de intervención, no de investigación descriptiva; «fortalecer» no tiene criterio de medición y el problema describe ausencia de delimitación de funciones, no una deficiencia de gestión demostrada en la escuela.
A15: G2 | B15: Objetivo general | C15: =Calificación!F41 -> 5 | D15: =IF(C15>=Rúbrica!$D$6,"Logrado","No logrado") -> Logrado | E15: Verbo «diseñar», un solo propósito y delimitación completa (escuela, localidad, periodo). Corresponde a la pregunta, pero no al problema ni a la Introducción («analizar y definir las funciones»). El «modelo de gestión estratégica» no se define en el marco teórico.
A16: G2 | B16: Objetivos específicos | C16: =Calificación!F42 -> 1.625 | D16: =IF(C16>=Rúbrica!$D$6,"Logrado","No logrado") -> No logrado | E16: El OE1 acumula cinco objetos en una sola enunciación («conocimientos, funciones, fortalezas, limitaciones y procesos»). El OE2 supone un «diagnóstico realizado», que sería el resultado del OE1. El OE3 (evaluar la aplicación de la estrategia) requiere implementar la estrategia y medir resultados, lo que no es viable dentro del periodo 2026-2 ni está en el objetivo general. Los tres repiten la cláusula de contexto completa, lo que alarga innecesariamente la redacción.
A17: G2 | B17: Justificación | C17: =Calificación!F43 -> 2.5 | D17: =IF(C17>=Rúbrica!$D$6,"Logrado","No logrado") -> No logrado | E17: Presenta tres dimensiones (académica, profesional, social) y vincula con el problema. No contiene ninguna cita: afirmaciones como «una estructura administrativa formal es clave para optimizar la toma de decisiones» y «las deficiencias en la gestión pueden provocar la deserción» carecen de sustento y se redactan como hechos. El verbo «demuestra» no corresponde a un estudio descriptivo. No se plantea viabilidad ni el aporte específico a Elizalde FC o al programa de Administración Deportiva. El uso de «Mientras que» es inadecuado como conector.
A18: G2 | B18: Antecedentes (Capítulo 2) | C18: =Calificación!F44 -> 3.625 | D18: =IF(C18>=Rúbrica!$D$6,"Logrado","No logrado") -> Logrado | E18: Organizados por ámbitos, con síntesis y brecha explícitas (único trabajo del grupo con este cierre). Cobertura internacional (España 2025; Cuba 2024), nacional (Caldas 2023; Antioquia 2010) y distrital (Pedreros, 2016). Fuentes de 2010 y 2016 superan el rango de actualidad; el trabajo de Pedreros se describe como «trabajo de grado» en el problema y «trabajo de posgrado» en antecedentes, y no tiene enlace de repositorio. La Resolución 639 de 2021 es normativa, no antecedente investigativo. Los antecedentes de Zapata et al. (2010) y Pedreros (2016) carecen de objetivo, método y resultados. Se duplican párrafos del problema.
A19: G2 | B19: Marco teórico y conceptual (Capítulo 2) | C19: =Calificación!F45 -> 2.5 | D19: =IF(C19>=Rúbrica!$D$6,"Logrado","No logrado") -> No logrado | E19: Se limita a un marco conceptual de cinco definiciones, construidas casi en su totalidad por citas secundarias (Cardona y Padierna, 2017; García y Pradas, 2017; Pedrosa, 2016; Méndez, 2014, «como se citó en» Barahona Vinasco et al., 2023). No hay marco teórico: falta el modelo de gestión estratégica y la teoría administrativa que fundamente las funciones. Inconsistencia interna: se anuncian «cinco funciones» (planear, organizar, dirigir, ejecutar, controlar) y luego se desarrollan cuatro. «Pedrosa, 2016» difiere del autor de la lista («Pedreros, 2016»).
A20: G2 | B20: APA 7 y redacción (transversal) | C20: =Calificación!F46 -> 2 | D20: =IF(C20>=Rúbrica!$D$6,"Logrado","No logrado") -> No logrado | E20: Correspondencia cita–referencia casi completa, pero con tres fallas: «Pedrosa (2016)» vs. «Pedreros (2016)»; la Resolución 639 de 2021 se cita a través de una página del IDRD sin referencia propia; Cardona y Padierna (2017) y García y Pradas (2017) figuran en la lista como fuentes primarias mientras se citan como secundarias. Ley 181 de 1995 no sigue el formato APA 7 (falta Congreso de la República de Colombia como autor y año entre paréntesis tras el título). Faltan DOI o URL en Méndez Álvarez et al. (2024) y Pedreros (2016). Introducción con errores ortográficos y sintácticos recurrentes, portada con errores («Faculta de Medio Ambiente», «caldas»), Metodología y Resultados con texto de plantilla, y declaración de IA incompleta y mal redactada.
A21: G3 | B21: Descripción del problema | C21: =Calificación!G39 -> 3.875 | D21: =IF(C21>=Rúbrica!$D$6,"Logrado","No logrado") -> Logrado | E21: Mejor estructurado del curso en niveles internacional, nacional y local, con datos territoriales verificables (Secretaría Distrital de Planeación, 2024: 85,9 % de manzanas de estrato 1 de Kennedy en Patio Bonito; Alcaldía Local de Kennedy, 2026: más de 2.000 cupos gratuitos) y vacío explícito. Debilidades: no se aporta ninguna cifra sobre las escuelas (número en Patio Bonito, ingresos, deserción, cierres), de modo que el problema —la dificultad de sostenibilidad financiera— no se evidencia; el propio texto señala que la oferta gratuita «no permite afirmar» dificultades financieras. Faltan causas y consecuencias. Los datos de estratos se repiten tres veces (Introducción, Contexto y Justificación). Patio Bonito se denomina indistintamente «barrio», «UPZ» y «localidad».
A22: G3 | B22: Pregunta problema | C22: =Calificación!G40 -> 5 | D22: =IF(C22>=Rúbrica!$D$6,"Logrado","No logrado") -> Logrado | E22: Interrogante descriptivo, único, con objeto, población, lugar y periodo bien delimitados. «En función de las condiciones socioeconómicas» obliga a definir cómo se medirá esa variable.
A23: G3 | B23: Objetivo general | C23: =Calificación!G41 -> 5 | D23: =IF(C23>=Rúbrica!$D$6,"Logrado","No logrado") -> Logrado | E23: Verbo «caracterizar», un propósito, contexto y periodo completos, y concordante con la pregunta. No incluye «crecimiento institucional», que sí se desarrolla en antecedentes y marco teórico.
A24: G3 | B24: Objetivos específicos | C24: =Calificación!G42 -> 3.375 | D24: =IF(C24>=Rúbrica!$D$6,"Logrado","No logrado") -> Logrado | E24: OE1 (identificar) es medible y acotado. OE2 combina tres objetos (estrategias, condiciones socioeconómicas y factores asociados a la sostenibilidad) y exige un análisis relacional que la pregunta descriptiva no contempla. OE3 (proponer lineamientos) es de nivel proyectivo y no está contenido en el objetivo general.
A25: G3 | B25: Justificación | C25: =Calificación!G43 -> 4.375 | D25: =IF(C25>=Rúbrica!$D$6,"Logrado","No logrado") -> Logrado | E25: Desarrolla las perspectivas académica, social y práctica con fuentes (Pachau Torres et al., 2026; Secretaría Distrital de Planeación, 2024; Altamar Bruno et al., 2020). Incluye la limitación de no generalizar. No expone viabilidad (acceso a las escuelas, número de unidades, instrumentos). Extensa (cinco párrafos) y con reiteración del párrafo social sobre la oferta gratuita.
A26: G3 | B26: Antecedentes (Capítulo 2) | C26: =Calificación!G44 -> 4.25 | D26: =IF(C26>=Rúbrica!$D$6,"Logrado","No logrado") -> Logrado | E26: Tres niveles, con síntesis de tendencias y brecha (modelo del curso). Los estudios incluyen objetivo, método y resultado. Limitaciones: tres de los siete estudios nacionales y locales son trabajos de grado o planes de negocio; el antecedente de Mora Poveda (2021) es de formación musical, no deportiva; un antecedente local se cita como «MetaFlip, s/f» (nombre de un visor de repositorio, no el autor). La cita de Rodríguez Castiblanco y Pérez Cortes (2019) remite a una entrada de referencia sin autores.
A27: G3 | B27: Marco teórico y conceptual (Capítulo 2) | C27: =Calificación!G45 -> 1.875 | D27: =IF(C27>=Rúbrica!$D$6,"Logrado","No logrado") -> No logrado | E27: Cinco conceptos con definiciones de dos a tres líneas; tres sin fuente (estrategias de marketing, crecimiento institucional, escuelas de formación) y dos sustentadas solo en Gutiérrez Montaña (2008), que no aparece en la lista de referencias. No hay marco teórico: Fullerton y Merz (2008), citados en la Introducción, no se retoman. No se definen variables ni dimensiones medibles de sostenibilidad financiera o de condiciones socioeconómicas (por ejemplo, estrato). Al final del apartado quedan dos citas sueltas («(Informe de Gestión a diciembre | IDRD…, s/f)» y «(Rodríguez, 2015)») sin texto asociado.
A28: G3 | B28: APA 7 y redacción (transversal) | C28: =Calificación!G46 -> 1.125 | D28: =IF(C28>=Rúbrica!$D$6,"Logrado","No logrado") -> No logrado | E28: Uso sistemático de paréntesis en citas narrativas: «(Fullerton & Merz, 2008) plantean», «(Torres et al., 2026), mediante…», «(Calahorro-López y Ratkai (2024)», «(Ministerio del Deporte, 2024.)», «((Instituto Distrital… [IDRD], 2026)». La misma fuente se cita como «Torres et al., 2026» y «Pachau Torres et al., 2026» y figura dos veces en la lista (una con autores repetidos). 11 de 20 citas no se localizan por autor-año porque las referencias están escritas con el título de la página como autor («Vista de Los clubes de fútbol europeos…», «Parque Patio Bonito | IDRD…», «MetaFlip», «3._diagnostico_de_pdl_de_kennedy»). Gutiérrez Montaña (2008) no tiene referencia. Se emplea «s/f» en lugar de «s. f.», se mantiene la marca «utm_source=chatgpt.com» en un enlace y hay títulos en mayúsculas. Quedan en el documento textos de plantilla (Glosario, «Acá va el resumen») y el nombre del asesor con error («Mnedoza»).
A29: G4 | B29: Descripción del problema | C29: =Calificación!H39 -> 2.5 | D29: =IF(C29>=Rúbrica!$D$6,"Logrado","No logrado") -> No logrado | E29: El texto describe la situación local (cruces de horario, canales de difusión, inscripción), pero no distingue los niveles internacional, nacional y local, y los encabezados «¿Qué?», «¿En quiénes?», «¿Dónde?», «¿En qué periodo?» son guion de trabajo sin redactar. La sección «Magnitud» reporta que «entre el 60 % y el 80 % de la población universitaria en Colombia» es inactiva y atribuye la cifra a Sevil Serrano et al. (2017), estudio de autores españoles con 901 participantes cuyo resumen no indica una muestra colombiana (verificado en el resumen de la fuente), y a Ramírez-Vélez et al. (2016); y reporta 48 % a 67 % de barreras «en el contexto universitario colombiano» con Franco-Idárraga et al. (2022), cuya población es de Manizales. No hay ningún dato de la sede (equipos inscritos, partidos perdidos por W, abstención), aunque el texto habla de «alta tasa de abstención» y «constante pérdida de puntos por w». Causas y consecuencias están desarrolladas (individual, operativa, gestión) pero sin respaldo empírico. El problema presupone la respuesta (que las barreras son logísticas) y el vacío solo se formula en Antecedentes. Hay una oración incompleta («La falta de articulación entre sus cargas horarias académicas y la organización del torneo.»).
A30: G4 | B30: Pregunta problema | C30: =Calificación!H40 -> 5 | D30: =IF(C30>=Rúbrica!$D$6,"Logrado","No logrado") -> Logrado | E30: Interrogante único, concreto y con población, escenario y periodo. Es extensa por la enumeración entre paréntesis y por «según su frecuencia e intensidad percibida», que ya define el instrumento. La lista cerrada de cuatro barreras limita la posibilidad de hallar otras.
A31: G4 | B31: Objetivo general | C31: =Calificación!H41 -> 5 | D31: =IF(C31>=Rúbrica!$D$6,"Logrado","No logrado") -> Logrado | E31: Verbo «determinar» medible, con delimitación completa. Duplica la pregunta; no hay inconsistencia, pero la medición de «frecuencia e intensidad percibida» debe definirse en la metodología (que en este documento está sin elaborar).
A32: G4 | B32: Objetivos específicos | C32: =Calificación!H42 -> 3.25 | D32: =IF(C32>=Rúbrica!$D$6,"Logrado","No logrado") -> Logrado | E32: OE1 introduce «hábitos de participación», variable ausente en la pregunta. OE2 y OE3 se solapan (incidencia percibida vs. jerarquización por frecuencia e intensidad). OE4 (proponer estrategias) pertenece a otro nivel (aplicado) y no está en el general.
A33: G4 | B33: Justificación | C33: =Calificación!H43 -> 3.125 | D33: =IF(C33>=Rúbrica!$D$6,"Logrado","No logrado") -> Logrado | E33: Tres líneas (social e institucional, práctica, académica) con destinatarios identificados (coordinación del torneo). Sustento débil: «la literatura científica confirma que la práctica deportiva recreativa… previene el abandono temprano» se respalda con Ramírez-Vélez et al. (2016), estudio sobre barreras percibidas y obesidad abdominal. Redacción en primera persona («nuestra sede», «encontramos»). No se expone viabilidad (acceso a la población, tamaño).
A34: G4 | B34: Antecedentes (Capítulo 2) | C34: =Calificación!H44 -> 3.875 | D34: =IF(C34>=Rúbrica!$D$6,"Logrado","No logrado") -> Logrado | E34: Cinco revisiones sistemáticas (2019 a 2026) resumidas en una tabla y agrupadas por temas, con límites de la evidencia y vacío explícito: el esquema mejor organizado del curso. Limitaciones: todas son revisiones generales de actividad física; no hay estudios sobre torneos internos, deporte universitario o logística, ni nacionales o locales. El estilo es coloquial («algo parecido», «pesaban», «sirve poco»). No se explica la estrategia de selección de las revisiones.
A35: G4 | B35: Marco teórico y conceptual (Capítulo 2) | C35: =Calificación!H45 -> 3.875 | D35: =IF(C35>=Rúbrica!$D$6,"Logrado","No logrado") -> Logrado | E35: Selección teórica pertinente (modelo jerárquico de restricciones del ocio: Crawford et al., 1991; Jackson, 1988) y cuatro subdimensiones operativas. La sección «Logística deportiva y gestión de actividades deportivas» (tres párrafos) no tiene ninguna cita. Algunas fuentes no respaldan lo afirmado: Flórez Saavedra y Herrada Urriago (2021, tesis de Enfermería sobre actividad física) define «barreras logísticas»; Cardona-Mejía y Padierna-Cardona (2021, sobre programas académicos) respalda el estado de las canchas; y la afirmación de que los cruces de horario son «el factor que con mayor frecuencia genera… derrotas por W» se atribuye a dos estudios que no tratan torneos. Redacción en primera persona plural. La subdimensión «trámites de inscripción y equipamiento» incorpora un elemento (equipamiento) que no está en el objetivo.
A36: G4 | B36: APA 7 y redacción (transversal) | C36: =Calificación!H46 -> 2.5 | D36: =IF(C36>=Rúbrica!$D$6,"Logrado","No logrado") -> No logrado | E36: Citas: «(Crawford et al., 1991) & (Jackson, 1988) quienes plantean»; falta el punto final antes de la cita en varios párrafos; Crawford et al. (1991a) se cita con y sin sufijo. Referencias: Crawford et al. (1991a y 1991b) y Sevil Serrano et al. (2017a y 2017b) son entradas idénticas; las listas de autores de Franco-Idárraga et al. (2022) y Sevil Serrano et al. se repiten completas dentro de la misma entrada; Brown, Ferreira Silva, Mella-Norambuena, Pan y Sim aparecen después de Sevil Serrano (rompen el orden alfabético); tesis rotulada «Bachelor thesis, Enfermería» en inglés. Portada con «Kildeman», «Figeroa», «Monografía presentado… título de en»; Metodología y Resultados con texto de plantilla.
A37: G5 | B37: Descripción del problema | C37: =Calificación!I39 -> 2.125 | D37: =IF(C37>=Rúbrica!$D$6,"Logrado","No logrado") -> No logrado | E37: Se organiza en niveles internacional, nacional y local. Los niveles internacional y nacional se construyen con informes institucionales (FIFA, 2023a, 2023b; UEFA, 2019; DIMAYOR, 2026; Federación Colombiana de Fútbol, 2025; Ministerio del Deporte, 2025) que no tienen referencia en la lista, de modo que no son verificables. El nivel local no describe una situación en la sede; solo justifica la elección de la población. No se enuncia el vacío. La sección «A quiénes afecta y qué consecuencias tiene» contiene fragmentos sin sujeto («a nivel académico vemos…»), minúsculas iniciales («bosa porvenir»), primera persona («analizamos»), y atribuye a Martínez Mina (2025) afirmaciones sobre patrocinios y contratos. En «Magnitud» se afirma que «más del 70 % de las marcas… destinan la totalidad de su presupuesto… al fútbol masculino» (Clavijo Vidal y Vidal Cañas, 2021, trabajo de grado) y que las transmisiones han sido «menos del 15 %» citando un reglamento de competencia, que no es fuente de series históricas. Persisten las etiquetas de plantilla «¿Qué?», «¿En quienes?», y se denomina «Facultad de Administración Deportiva» a la Facultad de Medio Ambiente y Recursos Naturales.
A38: G5 | B38: Pregunta problema | C38: =Calificación!I40 -> 3.25 | D38: =IF(C38>=Rúbrica!$D$6,"Logrado","No logrado") -> Logrado | E38: Interrogante único y abierto (¿cuál es la percepción…?). No hay coherencia en la población: la etiqueta «¿En quiénes?» menciona «estudiantes femeninas», la pregunta alude a las estudiantes del proyecto curricular y la Introducción y la Justificación a las «experiencias de las jugadoras». «Influencia» sugiere causalidad que un estudio de percepción no puede establecer, y «visibilidad» no está definida. La percepción de estudiantes tiene escaso valor como evidencia sobre el marketing de una liga si no se justifica su conocimiento del tema.
A39: G5 | B39: Objetivo general | C39: =Calificación!I41 -> 5 | D39: =IF(C39>=Rúbrica!$D$6,"Logrado","No logrado") -> Logrado | E39: Verbo «analizar», un propósito, población, escenario y periodo explícitos; reproduce la pregunta. Su alcance se limita a percepciones y excluye lo que la Introducción y el título anuncian (narrativas de jugadoras).
A40: G5 | B40: Objetivos específicos | C40: =Calificación!I42 -> 2.5 | D40: =IF(C40>=Rúbrica!$D$6,"Logrado","No logrado") -> No logrado | E40: OE1 mezcla tres niveles de visibilidad (mediática, digital e institucional) en una sola enunciación. OE2 («identificar la lectura analítica… sobre aplicación del marketing») no es operacionalizable. OE3 introduce «sostenibilidad profesional» sin definición. OE4 está redactado con error gramatical («Proponer estrategias de marketing deportivo y potenciar la visibilidad») y excede el nivel del objetivo general.
A41: G5 | B41: Justificación | C41: =Calificación!I43 -> 1.875 | D41: =IF(C41>=Rúbrica!$D$6,"Logrado","No logrado") -> No logrado | E41: Tres párrafos que hablan de «experiencias de las jugadoras», de la formación de las estudiantes y de la delimitación 2020-2026 (distinta de 2026-3). Las fuentes son un trabajo de grado y los informes de FIFA que no están en las referencias. No se plantean viabilidad ni utilidad concreta para la gestión deportiva.
A42: G5 | B42: Antecedentes (Capítulo 2) | C42: =Calificación!I44 -> 1.75 | D42: =IF(C42>=Rúbrica!$D$6,"Logrado","No logrado") -> No logrado | E42: La tabla incluye cuatro fuentes, una de las cuales es el Reglamento de la Liga (no es investigación) y dos son trabajos de grado. Las filas registran un hallazgo de una línea sin objetivo, método ni población; la de Cabrera Camacho y Hortúa Calderón (2021) es un fragmento («El posicionamiento de marca de las jugadoras»). No hay antecedentes internacionales ni síntesis ni vacío. El párrafo introductorio reproduce la fórmula de otro trabajo del curso («Para no presentarlas una por una, se agruparon temáticamente»).
A43: G5 | B43: Marco teórico y conceptual (Capítulo 2) | C43: =Calificación!I45 -> 0.625 | D43: =IF(C43>=Rúbrica!$D$6,"Logrado","No logrado") -> No logrado | E43: La «Referencia teórica» consta de tres apartados (Contexto global, Panorama nacional, Estudios locales) que repiten los antecedentes; no desarrollan teoría ni definen marketing deportivo, patrocinio, visibilidad, imagen de las deportistas o percepción. La única fuente del primer apartado es «Liga de Dinero del Fútbol Deloitte 2026, s/f» sin autor ni enlace; el segundo apartado afirma conclusiones («es importante desarrollar mejores estrategias») que no se sustentan en el texto. Redacción coloquial («muchas veces», «buenos resultados»).
A44: G5 | B44: APA 7 y redacción (transversal) | C44: =Calificación!I46 -> 0.625 | D44: =IF(C44>=Rúbrica!$D$6,"Logrado","No logrado") -> No logrado | E44: Solo 6 referencias frente a 12 fuentes citadas: faltan FIFA (2023a, 2023b), UEFA (2019), DIMAYOR (2026), Federación Colombiana de Fútbol (2025) y Ministerio del Deporte (2025). «Clavijo Silva y Vidal Cañas» (texto) vs. «Clavijo Vidal» (lista). «Martinez Mina (2025)» sin tilde y titulada en mayúsculas. «REGLAMENTO-LIGA-FEMENINA-2026. (s/f)» y «Liga de Dinero del Fútbol Deloitte 2026. (s/f)» no tienen autor corporativo ni enlace. Trabajos de grado sin enlace al repositorio y con errores en el título («Desarollo e implementacion… futbol»). El título del trabajo coincide, salvo la palabra «femenino», con el del trabajo de grado de Clavijo Vidal y Vidal Cañas (2021) que figura en la lista de referencias del propio documento. Persisten textos de plantilla (resumen, abstract, metodología y resultados) y la declaración de IA está en Anexos sin herramienta ni versión.
A45: G6 | B45: Descripción del problema | C45: =Calificación!J39 -> 3.875 | D45: =IF(C45>=Rúbrica!$D$6,"Logrado","No logrado") -> Logrado | E45: Estructura internacional-nacional-local con evidencia citada (Ferreira-Barbosa et al., 2022; Zeithaml et al., 1996; Do & Dang, 2026; Matus-Castillo et al., 2023; Rubio Silva et al., 2023; IDRD, 2022) y vacío formulado de manera explícita. Debilidad principal: el texto reconoce que no existen cifras de usuarios, retención o abandono del gimnasio (el nivel local carece de datos), de modo que el «problema» es una brecha de conocimiento y no una situación documentada. Las consecuencias se enuncian en condicional («podrían disminuir su uso») y no se identifican causas. La Introducción y el problema reiteran la misma idea. Mezcla de formatos numéricos («55.6%» y «55.6 %»).
A46: G6 | B46: Pregunta problema | C46: =Calificación!J40 -> 5 | D46: =IF(C46>=Rúbrica!$D$6,"Logrado","No logrado") -> Logrado | E46: Interrogante único, con variables, población, escenario y periodo. «¿Cómo se asocia…?» admite una respuesta cualitativa; «¿Qué relación existe…?» o «¿En qué medida se asocia…?» expresa mejor el alcance correlacional. La pregunta se repite como título en la portada, con una extensión que excede la de un título.
A47: G6 | B47: Objetivo general | C47: =Calificación!J41 -> 5 | D47: =IF(C47>=Rúbrica!$D$6,"Logrado","No logrado") -> Logrado | E47: Verbo «analizar» con adverbio «cuantitativamente», un solo propósito, variables y delimitación completas. Responde a la pregunta.
A48: G6 | B48: Objetivos específicos | C48: =Calificación!J42 -> 3.375 | D48: =IF(C48>=Rúbrica!$D$6,"Logrado","No logrado") -> Logrado | E48: Los cuatro objetivos son secuenciales (caracterizar, describir, relacionar, comparar) y cubren el general. El OE3 incluye «(correlación de Spearman o regresión)» y el OE4 «(Mann-Whitney o Kruskal-Wallis)»: la técnica estadística corresponde a la metodología y la disyunción «o» deja la decisión abierta. El OE4 está condicionado a que cada subgrupo tenga al menos 30 respuestas, cuando la meta mínima de la muestra es 85, de modo que no puede garantizarse la comparación por tres variables.
A49: G6 | B49: Justificación | C49: =Calificación!J43 -> 2.5 | D49: =IF(C49>=Rúbrica!$D$6,"Logrado","No logrado") -> No logrado | E49: Tres párrafos (conocimiento de la relación, utilidad para la administración, pertinencia para la Administración Deportiva). El primer enunciado es circular («es importante porque busca conocer…»), el sustento se reduce a Ferreira-Barbosa et al. (2022) y Zeithaml et al. (1996), no se retoma el vacío ni se indican beneficiarios con precisión ni viabilidad. El segundo párrafo presenta una coma en lugar de punto («…de la universidad, conocer la opinión de los estudiantes…»).
A50: G6 | B50: Antecedentes (Capítulo 2) | C50: =Calificación!J44 -> 4.625 | D50: =IF(C50>=Rúbrica!$D$6,"Logrado","No logrado") -> Logrado | E50: Ocho estudios (2021-2026) agrupados en cuatro temas, con muestra, método, resultado y aporte para la tesis, y síntesis con vacío (el apartado mejor construido del curso). Se declara la estrategia de búsqueda, aunque limitada a «la web abierta» y a índices de acceso abierto. Los antecedentes colombianos son de actividad física y barreras, no de calidad de servicio; no hay antecedente local de la Universidad Distrital. Los párrafos de Ferreira-Barbosa, Do y Dang y Matus-Castillo se repiten del planteamiento.
A51: G6 | B51: Marco teórico y conceptual (Capítulo 2) | C51: =Calificación!J45 -> 5 | D51: =IF(C51>=Rúbrica!$D$6,"Logrado","No logrado") -> Logrado | E51: Sustento teórico pertinente y con fuentes primarias: SERVQUAL (Parasuraman et al., 1988), SERVPERF (Cronin & Taylor, 1992), QUESC (Kim & Kim, 1995), teoría del comportamiento planificado (Ajzen, 1991) y Zeithaml et al. (1996). Justifica la elección SERVPERF y define la variable dependiente como intención declarada. No define «satisfacción», que se emplea como mediadora en la argumentación. La hipótesis se ubica en el marco teórico.
A52: G6 | B52: APA 7 y redacción (transversal) | C52: =Calificación!J46 -> 4.5 | D52: =IF(C52>=Rúbrica!$D$6,"Logrado","No logrado") -> Logrado | E52: Correspondencia cita–referencia completa en los capítulos 1 y 2. Errores menores: «(Do & Dang, 2026), Aunque…» (coma tras el paréntesis y mayúscula); mezcla de «&» y «y» en citas dentro y fuera de paréntesis; Parasuraman et al. (1988) sin DOI. Persisten marcas de trabajo no resueltas: «[COMPLETAR al terminar el Capítulo 4…]» en el Resumen y el Abstract, «[CONFIRMAR…]», «[firmas]» y «[fecha]» en la declaración de IA, y un Anexo G con un prompt reutilizable dentro de un documento de grado. Portada con «Monografía presentado» y «Centro Universitario Distrital Francisco José de Caldas».
A53: G7 | B53: Descripción del problema | C53: =Calificación!K39 -> 3.875 | D53: =IF(C53>=Rúbrica!$D$6,"Logrado","No logrado") -> Logrado | E53: Contexto internacional (Burton, 2015; Evans y Pfister, 2021), nacional (Ministerio del Deporte y ONU Mujeres, 2022: 13 % y 22 % de mujeres en representación legal; Ley 581 de 2000 modificada por Ley 2424 de 2024) y universitario (Pardo Calvache et al., 2024: 44 % y 29,7 %), con enunciado explícito del problema como falta de evidencia. Debilidades: los tres niveles se encuentran en la Introducción y no en la sección «Descripción del problema», que repite el argumento; no hay cifras del programa ni de la sede; las consecuencias se formulan como supuesto («la brecha podría comenzar a consolidarse»), que el propio texto reconoce como no probado. El marco normativo ocupa casi la mitad de la Introducción sin conexión directa con la pregunta. Se usa «anteproyecto» en lugar de monografía.
A54: G7 | B54: Pregunta problema | C54: =Calificación!K40 -> 5 | D54: =IF(C54>=Rúbrica!$D$6,"Logrado","No logrado") -> Logrado | E54: Interrogante único, con población, comparación, sede y periodo. Es extensa pero clara. «Situaciones de desigualdad» debe operacionalizarse (oportunidades, trato, integración).
A55: G7 | B55: Objetivo general | C55: =Calificación!K41 -> 5 | D55: =IF(C55>=Rúbrica!$D$6,"Logrado","No logrado") -> Logrado | E55: Verbo «analizar», un solo propósito, delimitación completa y concordancia con la pregunta. La comparación con compañeros hombres se declara en el objetivo.
A56: G7 | B56: Objetivos específicos | C56: =Calificación!K42 -> 5 | D56: =IF(C56>=Rúbrica!$D$6,"Logrado","No logrado") -> Logrado | E56: Tres verbos en infinitivo en orden creciente de complejidad (identificar, describir, comparar), alineados con el general. OE2 reúne tres dimensiones (oportunidades, trato, integración) que deben aparecer como categorías del instrumento. Tras los objetivos se incluye un párrafo metacomentario («Cada objetivo usa un solo verbo… siguiendo las orientaciones… de Tamayo y Tamayo, 2004») que no corresponde a un trabajo de grado.
A57: G7 | B57: Justificación | C57: =Calificación!K43 -> 4.375 | D57: =IF(C57>=Rúbrica!$D$6,"Logrado","No logrado") -> Logrado | E57: Es el único texto del curso que separa valor teórico, utilidad metodológica y viabilidad, y que declara riesgos (baja tasa de respuesta, sensibilidad del tema). Debilidades: el primer párrafo es un fragmento gramatical («Estudiar cómo perciben… permitiendo conocer,…»); incluye una nota pendiente («Falta confirmar con la coordinación…»); habla de «el autor» pese a que son tres integrantes; la utilidad metodológica se sustenta con Creswell y Creswell (2018) y con Pardo Calvache et al. (2024) sin explicar la relación.
A58: G7 | B58: Antecedentes (Capítulo 2) | C58: =Calificación!K44 -> 4.625 | D58: =IF(C58>=Rúbrica!$D$6,"Logrado","No logrado") -> Logrado | E58: Cinco estudios (2022-2026) organizados en tres ejes, con muestra, diseño, resultados y aporte, más un apartado «Vacío de conocimiento y aporte del estudio». Faltan los estudios de administración deportiva en Bogotá o en Colombia; los antecedentes deportivos corresponden a deportistas de España. Los cuatro estudios centrales (Bartual Figueras et al., 2022; Donoso Pérez et al., 2023; Iregui-Bohórquez et al., 2026; Oviedo Oviedo et al., 2024) no tienen referencia en la lista. Pardo Calvache et al. (2024) se describe en la Introducción y se repite en los antecedentes.
A59: G7 | B59: Marco teórico y conceptual (Capítulo 2) | C59: =Calificación!K45 -> 4.375 | D59: =IF(C59>=Rúbrica!$D$6,"Logrado","No logrado") -> Logrado | E59: Sustento teórico variado y con fuentes primarias (Jacobs, 1996; Sallee, 2011; Steele et al., 2002; Harris et al., 2014; Tinto, 1993), con cautelas explícitas sobre su aplicabilidad. Debilidades: la sección inicia con un objeto distinto al de la pregunta (ingreso y permanencia); la teoría de roles sociales se presenta con Grappendorf y Burton (2016), sin la fuente teórica original; las definiciones de «desigualdad de género» y «trayectoria académica» se encuentran en la Introducción, no en el marco.
A60: G7 | B60: APA 7 y redacción (transversal) | C60: =Calificación!K46 -> 3.125 | D60: =IF(C60>=Rúbrica!$D$6,"Logrado","No logrado") -> Logrado | E60: Cuatro antecedentes y el Acuerdo/Resolución UD (2026b) se citan sin referencia; Asamblea General de las Naciones Unidas (2015) y Hernández-Sampieri y Mendoza Torres (2018) figuran sin citarse. Cinco entradas (Grappendorf y Burton, Harris et al., Jacobs, Sallee, Steele et al.) aparecen duplicadas, la segunda vez fuera del orden alfabético. La lista usa «y» en las primeras entradas y «&» en las demás. Congreso (2000, 2024b) sin enlace. El comunicado de prensa del Ministerio se enlaza a un archivo alojado en un sitio de prensa privada. La declaración de IA está en primera persona del singular, sin modelo ni fechas de uso y conserva un campo «[opcional: sugerencias de claridad y coherencia en el texto]».
A61: G8 | B61: Descripción del problema | C61: =Calificación!L39 -> 5 | D61: =IF(C61>=Rúbrica!$D$6,"Logrado","No logrado") -> Logrado | E61: Descripción en cuatro niveles (internacional, regional, nacional, local) con cifras verificables (Deloitte, 2025: 692 a 1.880 millones de dólares; Ministerio del Deporte, 2023; El Espectador, 2023), tres tablas de magnitud, actores afectados y vacío formulado. Es el planteamiento más documentado del curso. Debilidades: más de la mitad de las fuentes son prensa (Semana, Infobae, Vanguardia, Vorágine, ESPN); el dato de la Superintendencia de Industria y Comercio (1.274 contratos; 46 %) se atribuye a un artículo de Vorágine cuyo título trata de otro asunto y corresponde a futbolistas (la Justificación lo reformula como «46 % de las futbolistas»); la extensión (aprox. 12 páginas) incluye detalles marginales (resultado de la final de 2023, jugadora de la selección en Brasil). El propio texto reconoce que el Ministerio no registra baloncesto femenino profesional bajo contrato formal, lo que cuestiona la existencia de la población de estudio.
A62: G8 | B62: Pregunta problema | C62: =Calificación!L40 -> 4.5 | D62: =IF(C62>=Rúbrica!$D$6,"Logrado","No logrado") -> Logrado | E62: Interrogante descriptivo con tres variables y periodo (2022-2025), claro y delimitado. Su viabilidad es incierta: el documento muestra que las ediciones de 2024 y 2025 no están registradas, que los clubes no publican presupuestos y que no hay contratos formales, de modo que la respuesta podría limitarse a constatar la ausencia de datos.
A63: G8 | B63: Objetivo general | C63: =Calificación!L41 -> 4.125 | D63: =IF(C63>=Rúbrica!$D$6,"Logrado","No logrado") -> Logrado | E63: Verbo «analizar» y delimitación completa, pero incorpora el método («mediante la revisión documental de fuentes federativas, estatales, normativas y de prensa especializada») y agrupa tres variables económicas en un solo enunciado.
A64: G8 | B64: Objetivos específicos | C64: =Calificación!L42 -> 3.25 | D64: =IF(C64>=Rúbrica!$D$6,"Logrado","No logrado") -> Logrado | E64: Cuatro objetivos en secuencia lógica. El OE1 es un paso previo (inventario de certámenes). El OE3 introduce la unidad de referencia (SMLMV), que es criterio de análisis. El OE4 incluye comparación con el baloncesto masculino y con tendencias internacionales, fuera de la delimitación declarada («la rama masculina considerada en sí misma»). La disponibilidad de datos para OE2 y OE3 no está asegurada.
A65: G8 | B65: Justificación | C65: =Calificación!L43 -> 5 | D65: =IF(C65>=Rúbrica!$D$6,"Logrado","No logrado") -> Logrado | E65: Cinco apartados (teórica, social, práctica, disciplinar, viabilidad) con entregables concretos (inventario, caracterización presupuestal, matriz comparativa) y limitación reconocida (la información financiera de los clubes no es de publicación obligatoria). Sustentada en Deloitte (2025), Torres-Romay y García-Mirón (2020), El Espectador (2023) y la Ley 1445 de 2011. Repite argumentos del problema.
A66: G8 | B66: Antecedentes (Capítulo 2) | C66: =Calificación!L44 -> 3.875 | D66: =IF(C66>=Rúbrica!$D$6,"Logrado","No logrado") -> Logrado | E66: Estructura internacional y nacional con síntesis del vacío. Incluye el informe del Ministerio del Deporte (2023) como antecedente más cercano, y estudios sobre brecha salarial y patrocinio (Pérez Gázquez y Barquero-Ruiz, 2024; Marín Malo, 2024; Torres-Romay y García-Mirón, 2020) y sobre fútbol (Martínez Mina et al., 2019; Marín y Rodríguez, 2019). Ningún antecedente trata baloncesto femenino y no hay antecedente local. Algunos estudios se describen sin método ni muestra.
A67: G8 | B67: Marco teórico y conceptual (Capítulo 2) | C67: =Calificación!L45 -> 5 | D67: =IF(C67>=Rúbrica!$D$6,"Logrado","No logrado") -> Logrado | E67: Dos cuerpos teóricos con fuentes de base (Szymanski, 2003; Rodríguez Guerrero, 2012; Meenaghan, 1991; Cornwell, 1995) y tres conceptos operativos con definición (presupuesto de club, brecha económica de género, SMLMV). La síntesis explica cómo las teorías se relacionan con la pregunta y reconoce que no permiten anticipar resultados. Los conceptos se apoyan en el informe del Ministerio y en Torres-Romay y García-Mirón (2020).
A68: G8 | B68: APA 7 y redacción (transversal) | C68: =Calificación!L46 -> 3.25 | D68: =IF(C68>=Rúbrica!$D$6,"Logrado","No logrado") -> Logrado | E68: Las referencias corresponden a las citas, pero dos fuentes con el mismo autor y año (Ministerio del Deporte, 2023, 23 de mayo; Ministerio del Deporte, 2023, agosto) carecen de sufijos a/b y el texto cita «Ministerio del Deporte, 2023» y «El Ministerio del Deporte, 2023» indistintamente; FIBA (2025a, 2025b) se cita como «FIBA, 2025». Szymanski (2003) y Cornwell (1995) se enlazan a ResearchGate en lugar de a DOI o a la editorial. Más de la mitad de la lista corresponde a prensa y a páginas web. Ley 181 de 1995 se incluye sin citarse en el texto. No hay Declaración de uso de IA; la IA solo se menciona en las notas de las tablas («Elaboración con ayuda de IA»).
A69: G9 | B69: Descripción del problema | C69: =Calificación!M39 -> 1.375 | D69: =IF(C69>=Rúbrica!$D$6,"Logrado","No logrado") -> No logrado | E69: Mantiene las etiquetas internacional, nacional y local, pero el nivel internacional se sustenta con Castro et al. (2019), estudio colombiano sobre un solo club, que se repite en el nivel nacional. No hay datos de magnitud (uso de herramientas en clubes, perfiles requeridos, oferta curricular), ni causas o consecuencias, y el vacío se formula como «no se sabe mucho». La Introducción emplea oraciones telegráficas y coloquiales («Para arreglar esto», «Quieren saber», «Son estratégicos»). Falta el espacio antes del paréntesis en las citas («tácticos(Castro et al., 2019)»).
A70: G9 | B70: Pregunta problema | C70: =Calificación!M40 -> 4.5 | D70: =IF(C70>=Rúbrica!$D$6,"Logrado","No logrado") -> Logrado | E70: Interrogante único, con población, objeto, escenario y año. «Potencial de las herramientas» es un constructo amplio sin definición operativa, y la capacidad de estudiantes de tercer semestre para valorar ese potencial no se justifica.
A71: G9 | B71: Objetivo general | C71: =Calificación!M41 -> 3.25 | D71: =IF(C71>=Rúbrica!$D$6,"Logrado","No logrado") -> Logrado | E71: Enunciado de unas 90 palabras que combina tres propósitos (analizar la percepción, identificar conocimiento-interés-valoración y comprender la relación con las competencias de formación). Excede la pregunta. Contiene la delimitación completa.
A72: G9 | B72: Objetivos específicos | C72: =Calificación!M42 -> 1.75 | D72: =IF(C72>=Rúbrica!$D$6,"Logrado","No logrado") -> No logrado | E72: Cada objetivo tiene entre 55 y 70 palabras, con listas de ejemplos y cláusulas finales («con el propósito de…», «teniendo en cuenta…»). OE1 reúne conocimiento, familiaridad e interés; OE3 introduce la relación con la formación recibida. Hay un error tipográfico («José d e Caldas») y falta el punto final en OE1.
A73: G9 | B73: Justificación | C73: =Calificación!M43 -> 1.875 | D73: =IF(C73>=Rúbrica!$D$6,"Logrado","No logrado") -> No logrado | E73: Tres apartados (relevancia social, utilidad práctica e insumo curricular, aporte disciplinar) con propósito claro para el programa, pero sin una sola cita. Emplea afirmaciones no sustentadas y en tono promocional («evidencia empírica rigurosa», «aporte significativo», «tecnologías de vanguardia», «escasez de investigaciones»). No expone viabilidad.
A74: G9 | B74: Antecedentes (Capítulo 2) | C74: =Calificación!M44 -> 1.75 | D74: =IF(C74>=Rúbrica!$D$6,"Logrado","No logrado") -> No logrado | E74: Solo tres estudios (Moya Delgado, 2025; Ati et al., 2024; Castro et al., 2019) sobre analítica y aprendizaje automático en fútbol; ninguno trata percepción de estudiantes ni formación en administración deportiva. Se sobredimensionan los hallazgos («minimiza casi en su totalidad el margen de error humano», «demostraron») y se generaliza de un club a «los clubes profesionales de Bogotá». El «antecedente local» describe la propia investigación. No hay síntesis ni vacío. Davidson et al. (2024), el estudio más cercano (percepción de profesionales), solo aparece en la tabla CRAAP.
A75: G9 | B75: Marco teórico y conceptual (Capítulo 2) | C75: =Calificación!M45 -> 3.125 | D75: =IF(C75>=Rúbrica!$D$6,"Logrado","No logrado") -> Logrado | E75: Tres categorías (herramientas y análisis táctico; toma de decisiones y rendimiento; formación y apropiación tecnológica) sustentadas en revisiones (Goes et al., 2021; Rico-González et al., 2022; Otero-Saborido et al., 2021; Caicedo-Parada et al., 2020), Seifert et al. (2013), Zimmer y Keiper (2021) y DigComp 2.2. Se incluye un marco institucional y normativo del programa y una tabla CRAAP de evaluación de fuentes. Faltan definiciones de «percepción» y «potencial», que son las variables del estudio. La cita «Riina et al., 2022» usa el nombre de pila del primer autor como apellido (corresponde a Vuorikari, Kluzer y Punie, 2022).
A76: G9 | B76: APA 7 y redacción (transversal) | C76: =Calificación!M46 -> 1.375 | D76: =IF(C76>=Rúbrica!$D$6,"Logrado","No logrado") -> No logrado | E76: Referencias con nombre de la página como autor («Generalidades | Administración Deportiva. (s. f.)», «Funciones y deberes. (s. f.). Minciencias»), con fuentes no oficiales para la ley (Scribd) y con una entrada corrupta («June 1, E. date, June 1, 2003 with amendments effective, 2010, January 1, & reserved, 2017 Copyright © 2017 American Psychological Association All rights. (s. f.). Ethical principles…»). «Riina, V., Stefano, K., & Yves, P. (2022)» invierte nombres y apellidos; Galicia Alarcón duplica su autor; Goes et al. usa iniciales en minúscula; Briggs Baffoe-Djan conserva «1.^(a) ed.»; Márquez et al. (s. f.) con título en mayúsculas y sin editorial. Portada con título de «Licenciado en Educación Infantil». Persisten instrucciones de plantilla (Referente teórico, Metodología, Resultados) y la Declaración de uso de IA está vacía.
A77: G10 | B77: Descripción del problema | C77: =Calificación!N39 -> 2.125 | D77: =IF(C77>=Rúbrica!$D$6,"Logrado","No logrado") -> No logrado | E77: Redacción formal y ordenada en niveles internacional, nacional y local, con vacío explícito. Sin embargo, no hay un problema documentado: el texto plantea una oportunidad tecnológica («podría constituirse en una herramienta de apoyo») y no una dificultad en la formación de competencias; no se aportan cifras de uso de realidad virtual, de oferta curricular ni de brechas de competencias, y las causas y consecuencias están ausentes. El nivel nacional se sustenta únicamente en una página institucional del MEN (2024) y el local no cita fuentes. La Introducción repite buena parte del problema.
A78: G10 | B78: Pregunta problema | C78: =Calificación!N40 -> 4.25 | D78: =IF(C78>=Rúbrica!$D$6,"Logrado","No logrado") -> Logrado | E78: Interrogante único con población, objeto y periodo. «Estudiantes del programa» incluye todos los semestres, lo que lleva a valorar la percepción de personas sin experiencia con la tecnología; «competencias establecidas en el perfil de egreso» exige especificar cuáles y no se retoman en el marco teórico. La sede no figura en la pregunta pero sí en el objetivo general.
A79: G10 | B79: Objetivo general | C79: =Calificación!N41 -> 5 | D79: =IF(C79>=Rúbrica!$D$6,"Logrado","No logrado") -> Logrado | E79: Verbo «analizar», un solo propósito y delimitación de programa, sede y periodo. Responde a la pregunta.
A80: G10 | B80: Objetivos específicos | C80: =Calificación!N42 -> 4.25 | D80: =IF(C80>=Rúbrica!$D$6,"Logrado","No logrado") -> Logrado | E80: Tres objetivos que cubren el general en secuencia lógica. «Reconocer» es un verbo de baja precisión para un resultado verificable. El OE2 incorpora el método («a partir de un listado construido con base en la literatura») y el OE3 reúne tres objetos (beneficios, posibilidades y limitaciones). Se presentan con viñetas y no con numeración.
A81: G10 | B81: Justificación | C81: =Calificación!N43 -> 3.75 | D81: =IF(C81>=Rúbrica!$D$6,"Logrado","No logrado") -> Logrado | E81: Ocho fuentes de revisiones sistemáticas (Radianti et al., 2020; Conrad et al., 2024; Santilli et al., 2025; Putranto et al., 2023; Pinargote Castro et al., 2024) y documentos institucionales (MEN, MinTIC, Icfes). Cubre el valor académico y el contexto colombiano. No expone el beneficio práctico concreto para el programa (por ejemplo, insumo curricular), ni la viabilidad; los párrafos nacionales sobre MinTIC e Icfes no se vinculan con la pregunta.
A82: G10 | B82: Antecedentes (Capítulo 2) | C82: =Calificación!N44 -> 3.5 | D82: =IF(C82>=Rúbrica!$D$6,"Logrado","No logrado") -> Logrado | E82: Tres niveles (internacional, nacional, local) con estructura repetida y consistente: qué hizo el estudio, por qué es pertinente y en qué se diferencia («sin embargo, no aborda…»). Los antecedentes internacionales son revisiones indexadas (2023-2025), pero los nacionales y locales son más débiles: un trabajo de grado sobre matemáticas en octavo grado (Chacón Gómez, 2022), una nota de prensa de la Facultad de Ingeniería y menciones al repositorio sin citar. Cabrera-Duffaut (2024) se presenta como autor único con verbo en plural; la fuente tiene tres autores. No hay síntesis integradora ni vacío al cierre de la sección.
A83: G10 | B83: Marco teórico y conceptual (Capítulo 2) | C83: =Calificación!N45 -> 4.5 | D83: =IF(C83>=Rúbrica!$D$6,"Logrado","No logrado") -> Logrado | E83: Tres referentes pertinentes y con fuentes de base (Kolb, 1984; Davis, 1989), articulados mediante un esquema de relación entre realidad virtual, experiencia simulada, percepción y competencias. El apartado «Percepción de los estudiantes» no tiene fuente; la definición de competencias profesionales tampoco. El aprendizaje experiencial y el TAM se desarrollan en dos párrafos cada uno. La cita de Cabrera-Duffaut (2024) repite el error de autoría.
A84: G10 | B84: APA 7 y redacción (transversal) | C84: =Calificación!N46 -> 1.875 | D84: =IF(C84>=Rúbrica!$D$6,"Logrado","No logrado") -> No logrado | E84: Citas narrativas entre paréntesis y con el verbo en plural para un autor único: «(Putranto et al., 2023) realizaron», «(Cabrera-Duffaut, 2024) desarrollaron», «(Kolb, 1984) plantea». Salgado García y Fernández Gualteros (2024), Primer piloto 5G y el repositorio EAN figuran por el título de la página; dos enlaces conservan el parámetro «utm_source=chatgpt.com». Putranto et al. (2023) está duplicada y la lista se divide en dos bloques alfabéticos. Cabrera-Duffaut (2024) está registrada con un solo autor y el título comienza con «Frontiers |». La declaración de IA es una frase entrecomillada en el cuerpo («Se utilizó ChatGPT para organizar las ideas…») y el anexo «Uso ético y transparente de la IA» está vacío.
A85: G11 | B85: Descripción del problema | C85: =Calificación!O39 -> 1.375 | D85: =IF(C85>=Rúbrica!$D$6,"Logrado","No logrado") -> No logrado | E85: La sección es breve (cuatro párrafos) y descriptiva: presenta el marketing digital como campo relevante, pero no un problema. Los niveles nacional y local no tienen fuentes ni datos (número de clubes, seguidores, publicaciones, inversión en comunicación). No hay magnitud, causas ni consecuencias. El vacío («producción académica nacional limitada») se afirma sin evidencia de búsqueda. La Introducción incluye lenguaje de proceso interno («La propuesta parte de una lluvia de ideas…») y la «Delimitación del tema» conserva las etiquetas de plantilla (¿Qué?, ¿En quiénes?, ¿Dónde?, ¿En qué periodo?). Romero-Jara et al. aparece como 2023 en la Introducción y 2024 en el problema y los antecedentes.
A86: G11 | B86: Pregunta problema | C86: =Calificación!O40 -> 4.5 | D86: =IF(C86>=Rúbrica!$D$6,"Logrado","No logrado") -> Logrado | E86: Interrogante correlacional claro, con variables, unidad de análisis, plataforma y periodo. Es la pregunta mejor operacionalizada del curso. Los clubes específicos y la muestra de publicaciones no se definen todavía.
A87: G11 | B87: Objetivo general | C87: =Calificación!O41 -> 5 | D87: =IF(C87>=Rúbrica!$D$6,"Logrado","No logrado") -> Logrado | E87: Verbo «determinar la relación», único propósito, variables, plataforma y periodo explícitos. Coincide con la pregunta.
A88: G11 | B88: Objetivos específicos | C88: =Calificación!O42 -> 3.375 | D88: =IF(C88>=Rúbrica!$D$6,"Logrado","No logrado") -> Logrado | E88: Seis objetivos que describen pasos del procedimiento de análisis (identificar frecuencia, clasificar formatos, calcular tasa de engagement, analizar la correlación, comparar formatos, interpretar). Los tres primeros son tareas de recolección y el sexto no tiene resultado verificable. Se podrían condensar en tres objetivos (describir, relacionar, comparar).
A89: G11 | B89: Justificación | C89: =Calificación!O43 -> 3.125 | D89: =IF(C89>=Rúbrica!$D$6,"Logrado","No logrado") -> Logrado | E89: Cuatro dimensiones (disciplinar, social, académica y práctica) con destinatarios identificados (departamentos de mercadeo, agencias, patrocinadores). Ninguna se sustenta con fuentes; el quinto párrafo es una explicación metodológica y no una justificación. No se presenta la viabilidad (acceso a datos públicos, herramienta de extracción).
A90: G11 | B90: Antecedentes (Capítulo 2) | C90: =Calificación!O44 -> 3.875 | D90: =IF(C90>=Rúbrica!$D$6,"Logrado","No logrado") -> Logrado | E90: Cuatro estudios (Filo et al., 2015; Aichner, 2019; Vale y Fernandes, 2018; Romero-Jara et al., 2024) con muestra, método, resultado y relevancia, y una síntesis breve. Todos son internacionales y tres tienen entre 7 y 11 años; no hay antecedentes de Colombia ni de Latinoamérica, a pesar de que la justificación afirma que son escasos. Las revisiones más recientes de la lista de referencias (Cao y Matsuoka, 2025; Einsle et al., 2023; Rai et al., 2025) no se utilizan. El «Vacío identificado» reitera la delimitación del estudio y no argumenta la brecha.
A91: G11 | B91: Marco teórico y conceptual (Capítulo 2) | C91: =Calificación!O45 -> 4.5 | D91: =IF(C91>=Rúbrica!$D$6,"Logrado","No logrado") -> Logrado | E91: Es el marco teórico más articulado con el diseño: marketing relacional (Morgan y Hunt, 1994), usos y gratificaciones (Katz et al., 1973), engagement, frecuencia y formato, con aclaraciones sobre lo que la medición con datos públicos puede y no puede inferir. Algunas definiciones (marketing deportivo, frecuencia, formato) no se sustentan con fuente. Verbos categóricos como «demuestra» (Aichner, 2019) no son coherentes con la cautela del resto del texto.
A92: G11 | B92: APA 7 y redacción (transversal) | C92: =Calificación!O46 -> 3.75 | D92: =IF(C92>=Rúbrica!$D$6,"Logrado","No logrado") -> Logrado | E92: Lista de referencias con formato APA 7 correcto, orden alfabético y DOI en todas las entradas. Tres referencias no se citan en el texto (Cao y Matsuoka, 2025; Einsle et al., 2023; Rai et al., 2025). Discrepancia de año en Romero-Jara et al. (2023 vs. 2024) entre secciones. Persisten instrucciones de plantilla («En el trabajo se debe indicar cuáles clubes serán incluidos…»; «Indicar la mejor opción de entrega de resultados…»), el encabezado «Declaración de uso de IA» está vacío y el texto de IA aparece en Anexos sin herramienta ni versión; la fecha se presenta como «07/10/2026».

Sheet Errores APA y redacción
A1: Errores de normas APA 7.ª edición, redacción y proceso metodológico
A2: Resumen por categoría y gravedad (fórmulas COUNTIFS sobre el registro) y registro detallado con ubicación y ejemplo.
A3: A. Resumen por categoría
A4: Categoría | B4: G1 | C4: G2 | D4: G3 | E4: G4 | F4: G5 | G4: G6 | H4: G7 | I4: G8 | J4: G9 | K4: G10 | L4: G11 | M4: Total
A5: Lista de referencias (APA 7) | B5: =COUNTIFS($B$26:$B$129,B$4,$C$26:$C$129,$A5) -> 1 | C5: =COUNTIFS($B$26:$B$129,C$4,$C$26:$C$129,$A5) -> 2 | D5: =COUNTIFS($B$26:$B$129,D$4,$C$26:$C$129,$A5) -> 2 | E5: =COUNTIFS($B$26:$B$129,E$4,$C$26:$C$129,$A5) -> 4 | F5: =COUNTIFS($B$26:$B$129,F$4,$C$26:$C$129,$A5) -> 2 | G5: =COUNTIFS($B$26:$B$129,G$4,$C$26:$C$129,$A5) -> 1 | H5: =COUNTIFS($B$26:$B$129,H$4,$C$26:$C$129,$A5) -> 3 | I5: =COUNTIFS($B$26:$B$129,I$4,$C$26:$C$129,$A5) -> 2 | ... L5: =COUNTIFS($B$26:$B$129,L$4,$C$26:$C$129,$A5) -> 0 | M5: =SUM(B5:L5) -> 24
A6: Citación en el texto (APA 7) | B6: =COUNTIFS($B$26:$B$129,B$4,$C$26:$C$129,$A6) -> 1 | C6: =COUNTIFS($B$26:$B$129,C$4,$C$26:$C$129,$A6) -> 2 | D6: =COUNTIFS($B$26:$B$129,D$4,$C$26:$C$129,$A6) -> 2 | E6: =COUNTIFS($B$26:$B$129,E$4,$C$26:$C$129,$A6) -> 2 | F6: =COUNTIFS($B$26:$B$129,F$4,$C$26:$C$129,$A6) -> 2 | G6: =COUNTIFS($B$26:$B$129,G$4,$C$26:$C$129,$A6) -> 2 | H6: =COUNTIFS($B$26:$B$129,H$4,$C$26:$C$129,$A6) -> 0 | I6: =COUNTIFS($B$26:$B$129,I$4,$C$26:$C$129,$A6) -> 3 | ... L6: =COUNTIFS($B$26:$B$129,L$4,$C$26:$C$129,$A6) -> 2 | M6: =SUM(B6:L6) -> 21
A7: Correspondencia cita–referencia | B7: =COUNTIFS($B$26:$B$129,B$4,$C$26:$C$129,$A7) -> 2 | C7: =COUNTIFS($B$26:$B$129,C$4,$C$26:$C$129,$A7) -> 1 | D7: =COUNTIFS($B$26:$B$129,D$4,$C$26:$C$129,$A7) -> 3 | E7: =COUNTIFS($B$26:$B$129,E$4,$C$26:$C$129,$A7) -> 0 | F7: =COUNTIFS($B$26:$B$129,F$4,$C$26:$C$129,$A7) -> 1 | G7: =COUNTIFS($B$26:$B$129,G$4,$C$26:$C$129,$A7) -> 0 | H7: =COUNTIFS($B$26:$B$129,H$4,$C$26:$C$129,$A7) -> 2 | I7: =COUNTIFS($B$26:$B$129,I$4,$C$26:$C$129,$A7) -> 0 | ... L7: =COUNTIFS($B$26:$B$129,L$4,$C$26:$C$129,$A7) -> 1 | M7: =SUM(B7:L7) -> 11
A8: Declaración de uso de IA | B8: =COUNTIFS($B$26:$B$129,B$4,$C$26:$C$129,$A8) -> 1 | C8: =COUNTIFS($B$26:$B$129,C$4,$C$26:$C$129,$A8) -> 1 | D8: =COUNTIFS($B$26:$B$129,D$4,$C$26:$C$129,$A8) -> 0 | E8: =COUNTIFS($B$26:$B$129,E$4,$C$26:$C$129,$A8) -> 1 | F8: =COUNTIFS($B$26:$B$129,F$4,$C$26:$C$129,$A8) -> 1 | G8: =COUNTIFS($B$26:$B$129,G$4,$C$26:$C$129,$A8) -> 1 | H8: =COUNTIFS($B$26:$B$129,H$4,$C$26:$C$129,$A8) -> 1 | I8: =COUNTIFS($B$26:$B$129,I$4,$C$26:$C$129,$A8) -> 1 | ... L8: =COUNTIFS($B$26:$B$129,L$4,$C$26:$C$129,$A8) -> 1 | M8: =SUM(B8:L8) -> 10
A9: Plantilla, portada y restos de edición | B9: =COUNTIFS($B$26:$B$129,B$4,$C$26:$C$129,$A9) -> 1 | C9: =COUNTIFS($B$26:$B$129,C$4,$C$26:$C$129,$A9) -> 1 | D9: =COUNTIFS($B$26:$B$129,D$4,$C$26:$C$129,$A9) -> 1 | E9: =COUNTIFS($B$26:$B$129,E$4,$C$26:$C$129,$A9) -> 1 | F9: =COUNTIFS($B$26:$B$129,F$4,$C$26:$C$129,$A9) -> 1 | G9: =COUNTIFS($B$26:$B$129,G$4,$C$26:$C$129,$A9) -> 2 | H9: =COUNTIFS($B$26:$B$129,H$4,$C$26:$C$129,$A9) -> 1 | I9: =COUNTIFS($B$26:$B$129,I$4,$C$26:$C$129,$A9) -> 0 | ... L9: =COUNTIFS($B$26:$B$129,L$4,$C$26:$C$129,$A9) -> 1 | M9: =SUM(B9:L9) -> 10
A10: Uso y calidad de las fuentes | B10: =COUNTIFS($B$26:$B$129,B$4,$C$26:$C$129,$A10) -> 0 | C10: =COUNTIFS($B$26:$B$129,C$4,$C$26:$C$129,$A10) -> 0 | D10: =COUNTIFS($B$26:$B$129,D$4,$C$26:$C$129,$A10) -> 0 | E10: =COUNTIFS($B$26:$B$129,E$4,$C$26:$C$129,$A10) -> 2 | F10: =COUNTIFS($B$26:$B$129,F$4,$C$26:$C$129,$A10) -> 1 | G10: =COUNTIFS($B$26:$B$129,G$4,$C$26:$C$129,$A10) -> 0 | H10: =COUNTIFS($B$26:$B$129,H$4,$C$26:$C$129,$A10) -> 1 | I10: =COUNTIFS($B$26:$B$129,I$4,$C$26:$C$129,$A10) -> 2 | ... L10: =COUNTIFS($B$26:$B$129,L$4,$C$26:$C$129,$A10) -> 2 | M10: =SUM(B10:L10) -> 11
A11: Consistencia de datos | B11: =COUNTIFS($B$26:$B$129,B$4,$C$26:$C$129,$A11) -> 1 | C11: =COUNTIFS($B$26:$B$129,C$4,$C$26:$C$129,$A11) -> 1 | D11: =COUNTIFS($B$26:$B$129,D$4,$C$26:$C$129,$A11) -> 1 | E11: =COUNTIFS($B$26:$B$129,E$4,$C$26:$C$129,$A11) -> 0 | F11: =COUNTIFS($B$26:$B$129,F$4,$C$26:$C$129,$A11) -> 1 | G11: =COUNTIFS($B$26:$B$129,G$4,$C$26:$C$129,$A11) -> 1 | H11: =COUNTIFS($B$26:$B$129,H$4,$C$26:$C$129,$A11) -> 0 | I11: =COUNTIFS($B$26:$B$129,I$4,$C$26:$C$129,$A11) -> 0 | ... L11: =COUNTIFS($B$26:$B$129,L$4,$C$26:$C$129,$A11) -> 0 | M11: =SUM(B11:L11) -> 5
A12: Redacción y ortografía | B12: =COUNTIFS($B$26:$B$129,B$4,$C$26:$C$129,$A12) -> 1 | C12: =COUNTIFS($B$26:$B$129,C$4,$C$26:$C$129,$A12) -> 2 | D12: =COUNTIFS($B$26:$B$129,D$4,$C$26:$C$129,$A12) -> 0 | E12: =COUNTIFS($B$26:$B$129,E$4,$C$26:$C$129,$A12) -> 1 | F12: =COUNTIFS($B$26:$B$129,F$4,$C$26:$C$129,$A12) -> 1 | G12: =COUNTIFS($B$26:$B$129,G$4,$C$26:$C$129,$A12) -> 0 | H12: =COUNTIFS($B$26:$B$129,H$4,$C$26:$C$129,$A12) -> 1 | I12: =COUNTIFS($B$26:$B$129,I$4,$C$26:$C$129,$A12) -> 1 | ... L12: =COUNTIFS($B$26:$B$129,L$4,$C$26:$C$129,$A12) -> 1 | M12: =SUM(B12:L12) -> 9
A13: Originalidad y pertinencia | B13: =COUNTIFS($B$26:$B$129,B$4,$C$26:$C$129,$A13) -> 0 | C13: =COUNTIFS($B$26:$B$129,C$4,$C$26:$C$129,$A13) -> 0 | D13: =COUNTIFS($B$26:$B$129,D$4,$C$26:$C$129,$A13) -> 0 | E13: =COUNTIFS($B$26:$B$129,E$4,$C$26:$C$129,$A13) -> 0 | F13: =COUNTIFS($B$26:$B$129,F$4,$C$26:$C$129,$A13) -> 1 | G13: =COUNTIFS($B$26:$B$129,G$4,$C$26:$C$129,$A13) -> 1 | H13: =COUNTIFS($B$26:$B$129,H$4,$C$26:$C$129,$A13) -> 0 | I13: =COUNTIFS($B$26:$B$129,I$4,$C$26:$C$129,$A13) -> 0 | ... L13: =COUNTIFS($B$26:$B$129,L$4,$C$26:$C$129,$A13) -> 0 | M13: =SUM(B13:L13) -> 3
A14: Total de hallazgos | B14: =SUM(B5:B13) -> 8 | C14: =SUM(C5:C13) -> 10 | D14: =SUM(D5:D13) -> 9 | E14: =SUM(E5:E13) -> 11 | F14: =SUM(F5:F13) -> 11 | G14: =SUM(G5:G13) -> 8 | H14: =SUM(H5:H13) -> 9 | I14: =SUM(I5:I13) -> 9 | ... M14: =SUM(M5:M13) -> 104
A16: B. Resumen por gravedad
A17: Gravedad | B17: G1 | C17: G2 | D17: G3 | E17: G4 | F17: G5 | G17: G6 | H17: G7 | I17: G8 | J17: G9 | K17: G10 | L17: G11 | M17: Total
A18: Alta | B18: =COUNTIFS($B$26:$B$129,B$17,$H$26:$H$129,$A18) -> 2 | C18: =COUNTIFS($B$26:$B$129,C$17,$H$26:$H$129,$A18) -> 1 | D18: =COUNTIFS($B$26:$B$129,D$17,$H$26:$H$129,$A18) -> 4 | E18: =COUNTIFS($B$26:$B$129,E$17,$H$26:$H$129,$A18) -> 3 | F18: =COUNTIFS($B$26:$B$129,F$17,$H$26:$H$129,$A18) -> 6 | G18: =COUNTIFS($B$26:$B$129,G$17,$H$26:$H$129,$A18) -> 0 | H18: =COUNTIFS($B$26:$B$129,H$17,$H$26:$H$129,$A18) -> 2 | I18: =COUNTIFS($B$26:$B$129,I$17,$H$26:$H$129,$A18) -> 3 | ... L18: =COUNTIFS($B$26:$B$129,L$17,$H$26:$H$129,$A18) -> 2 | M18: =SUM(B18:L18) -> 36
A19: Media | B19: =COUNTIFS($B$26:$B$129,B$17,$H$26:$H$129,$A19) -> 5 | C19: =COUNTIFS($B$26:$B$129,C$17,$H$26:$H$129,$A19) -> 8 | D19: =COUNTIFS($B$26:$B$129,D$17,$H$26:$H$129,$A19) -> 5 | E19: =COUNTIFS($B$26:$B$129,E$17,$H$26:$H$129,$A19) -> 6 | F19: =COUNTIFS($B$26:$B$129,F$17,$H$26:$H$129,$A19) -> 5 | G19: =COUNTIFS($B$26:$B$129,G$17,$H$26:$H$129,$A19) -> 3 | H19: =COUNTIFS($B$26:$B$129,H$17,$H$26:$H$129,$A19) -> 5 | I19: =COUNTIFS($B$26:$B$129,I$17,$H$26:$H$129,$A19) -> 2 | ... L19: =COUNTIFS($B$26:$B$129,L$17,$H$26:$H$129,$A19) -> 5 | M19: =SUM(B19:L19) -> 50
A20: Baja | B20: =COUNTIFS($B$26:$B$129,B$17,$H$26:$H$129,$A20) -> 1 | C20: =COUNTIFS($B$26:$B$129,C$17,$H$26:$H$129,$A20) -> 1 | D20: =COUNTIFS($B$26:$B$129,D$17,$H$26:$H$129,$A20) -> 0 | E20: =COUNTIFS($B$26:$B$129,E$17,$H$26:$H$129,$A20) -> 2 | F20: =COUNTIFS($B$26:$B$129,F$17,$H$26:$H$129,$A20) -> 0 | G20: =COUNTIFS($B$26:$B$129,G$17,$H$26:$H$129,$A20) -> 5 | H20: =COUNTIFS($B$26:$B$129,H$17,$H$26:$H$129,$A20) -> 2 | I20: =COUNTIFS($B$26:$B$129,I$17,$H$26:$H$129,$A20) -> 4 | ... L20: =COUNTIFS($B$26:$B$129,L$17,$H$26:$H$129,$A20) -> 1 | M20: =SUM(B20:L20) -> 18
A21: Control (debe coincidir con el total de A) | M21: =IF(SUM(M18:M20)=M14,"OK","REVISAR") -> OK
A24: C. Registro detallado
A25: N.º | B25: Grupo | C25: Categoría (resumen) | D25: Tipo de error | E25: Ubicación | F25: Descripción del error | G25: Ejemplo en el documento | H25: Gravedad
A26: 1 | B26: G1 | C26: Correspondencia cita–referencia | D26: Correspondencia cita–referencia | E26: Referencias | F26: 8 referencias sin cita en el texto | G26: Bruce (2016); Calvo-Ortega (2020); Gómez-Colell et al. (2017); Olabe Sánchez (2010, 2012); Ramon Vegas et al. (2019); Sainz de Baranda Andújar (2014a, 2014b) | H26: Alta
A27: 2 | B27: G1 | C27: Correspondencia cita–referencia | D27: Correspondencia cita–referencia | E27: Antecedentes y marco | F27: 4 citas sin referencia | G27: Coronel Puello (2024); Entman (1993); Jodelet (2008); Calvo Ortega y Gutiérrez San Miguel (2017) | H27: Alta
A28: 3 | B28: G1 | C28: Citación en el texto (APA 7) | D28: Cita en texto | E28: Antecedentes nacionales | F28: Cuatro autores citados por extenso en narrativa (APA 7 exige «et al.» desde la primera cita con tres o más autores) | G28: Zapata Correa, Durán-Palacio, Rodríguez Gómez y Restrepo Echavarría (2026) | H28: Media
A29: 4 | B29: G1 | C29: Consistencia de datos | D29: Datos inconsistentes | E29: Problema vs. antecedentes | F29: Cifra de Boczek et al. (2023) distinta entre secciones | G29: 8,2 % (problema, justificación) vs. «8,1 %» (antecedentes) | H29: Media
A30: 5 | B30: G1 | C30: Lista de referencias (APA 7) | D30: Lista de referencias | E30: Referencias | F30: Entradas sin volumen, páginas o DOI; sufijos a/b sin que ambas se citen | G30: Olabe Sánchez (2010) sin DOI; Calvo-Ortega (2020) y Ramon Vegas et al. (2019) sin volumen ni páginas | H30: Baja
A31: 6 | B31: G1 | C31: Redacción y ortografía | D31: Ortografía y redacción | E31: Objetivos y declaración IA | F31: Errores de ortografía y de construcción | G31: «relación de entre»; «genero»; «se utilizo»; «Monografía presentado» | H31: Media
A32: 7 | B32: G1 | C32: Plantilla, portada y restos de edición | D32: Restos de plantilla | E32: Preliminares y Resultados | F32: Texto instructivo sin retirar | G32: «Dedicatoria (opcional)»; «Palabras clave: (En cursiva)»; «Indicar la mejor opción de entrega…»; «Figura 1 Título en cursiva» | H32: Media
A33: 8 | B33: G1 | C33: Declaración de uso de IA | D33: Declaración de IA | E33: Cuerpo y Anexos | F33: Dos declaraciones con contenido distinto; ninguna indica herramienta, versión ni fecha de uso | G33: «Para la elaboración… se utilizo inteligencia artificial» / «Uso ético de la inteligencia artificial» | H33: Media
A34: 9 | B34: G2 | C34: Citación en el texto (APA 7) | D34: Cita en texto | E34: Marco conceptual | F34: Autor citado con nombre distinto al de la lista de referencias | G34: Pedrosa, 2016 (texto) vs. Pedreros (2016) (referencias) | H34: Media
A35: 10 | B35: G2 | C35: Correspondencia cita–referencia | D35: Correspondencia cita–referencia | E35: Problema y antecedentes | F35: Normativa citada sin referencia propia | G35: Resolución 639 de 2021 atribuida a «IDRD, s.f.» | H35: Media
A36: 11 | B36: G2 | C36: Citación en el texto (APA 7) | D36: Cita secundaria | E36: Marco conceptual / Referencias | F36: Fuente en lista de referencias y, a la vez, citada como secundaria | G36: Cardona y Padierna (2017) y García y Pradas (2017) «como se citó en» Barahona Vinasco et al. (2023) | H36: Media
A37: 12 | B37: G2 | C37: Lista de referencias (APA 7) | D37: Lista de referencias | E37: Referencias | F37: Legislación sin estructura APA 7 | G37: Ley 181 de 1995. Por el cual se dictan… (faltan autor corporativo y año entre paréntesis) | H37: Media
... A129: 104 | B129: G11 | C129: Declaración de uso de IA | D129: Declaración de IA | E129: Cuerpo y Anexos | F129: Encabezado vacío en el cuerpo; texto genérico en Anexos sin herramienta, versión ni fecha | G129: «se utilizó inteligencia artificial como herramienta de apoyo» | H129: Alta

Sheet Coherencia interna
A1: Coherencia interna entre componentes
A2: Cada vínculo se codifica 0 = no coherente, 1 = coherencia parcial, 2 = coherente (celdas azules = juicio del evaluador, editable).
A4: N.º | B4: Vínculo | C4: G1 | D4: G2 | E4: G3 | F4: G4 | G4: G5 | H4: G6 | I4: G7 | J4: G8 | K4: G9 | L4: G10 | M4: G11 | N4: Media (0 – 2) | O4: % de grupos con coherencia plena
A5: 1 | B5: Problema ↔ Pregunta problema | C5: 1 | D5: 1 | E5: 2 | F5: 2 | G5: 1 | H5: 2 | I5: 2 | J5: 2 | K5: 2 | L5: 2 | M5: 1 | N5: =AVERAGE(C5:M5) -> 1.6363636 | O5: =COUNTIF(C5:M5,2)/COUNT(C5:M5) -> 0.63636364
A6: 2 | B6: Pregunta problema ↔ Objetivo general | C6: 0 | D6: 2 | E6: 2 | F6: 2 | G6: 2 | H6: 2 | I6: 2 | J6: 2 | K6: 1 | L6: 2 | M6: 2 | N6: =AVERAGE(C6:M6) -> 1.7272727 | O6: =COUNTIF(C6:M6,2)/COUNT(C6:M6) -> 0.81818182
A7: 3 | B7: Objetivo general ↔ Objetivos específicos | C7: 1 | D7: 1 | E7: 1 | F7: 1 | G7: 1 | H7: 1 | I7: 2 | J7: 1 | K7: 1 | L7: 2 | M7: 1 | N7: =AVERAGE(C7:M7) -> 1.1818182 | O7: =COUNTIF(C7:M7,2)/COUNT(C7:M7) -> 0.18181818
A8: 4 | B8: Justificación ↔ Objetivo general / pregunta | C8: 1 | D8: 1 | E8: 2 | F8: 2 | G8: 1 | H8: 1 | I8: 2 | J8: 2 | K8: 1 | L8: 1 | M8: 1 | N8: =AVERAGE(C8:M8) -> 1.3636364 | O8: =COUNTIF(C8:M8,2)/COUNT(C8:M8) -> 0.36363636
A9: 5 | B9: Antecedentes y marco teórico ↔ pregunta, objetivos y metodología | C9: 0 | D9: 0 | E9: 1 | F9: 1 | G9: 0 | H9: 2 | I9: 1 | J9: 2 | K9: 1 | L9: 2 | M9: 2 | N9: =AVERAGE(C9:M9) -> 1.0909091 | O9: =COUNTIF(C9:M9,2)/COUNT(C9:M9) -> 0.36363636
B10: Índice de coherencia del grupo (0 – 100 %) | C10: =SUM(C5:C9)/(2*COUNT(C5:C9)) -> 0.3 | D10: =SUM(D5:D9)/(2*COUNT(D5:D9)) -> 0.5 | E10: =SUM(E5:E9)/(2*COUNT(E5:E9)) -> 0.8 | F10: =SUM(F5:F9)/(2*COUNT(F5:F9)) -> 0.8 | G10: =SUM(G5:G9)/(2*COUNT(G5:G9)) -> 0.5 | H10: =SUM(H5:H9)/(2*COUNT(H5:H9)) -> 0.8 | I10: =SUM(I5:I9)/(2*COUNT(I5:I9)) -> 0.9 | J10: =SUM(J5:J9)/(2*COUNT(J5:J9)) -> 0.9 | ... M10: =SUM(M5:M9)/(2*COUNT(M5:M9)) -> 0.7 | N10: =AVERAGE(C10:M10) -> 0.7
A12: Observaciones por vínculo y grupo
A13: N.º | B13: Grupo | C13: Vínculo | D13: Código | E13: Observación
A14: 1 | B14: G1 | C14: Problema ↔ Pregunta problema | D14: =C5 -> 1 | E14: La pregunta retoma la población y el fenómeno del problema (percepción de estudiantes), pero añade una cláusula ajena: «como referente para la gestión de comunicaciones institucionales de clubes deportivos».
A15: 2 | B15: G1 | C15: Pregunta problema ↔ Objetivo general | D15: =C6 -> 0 | E15: La pregunta indaga percepciones de estudiantes; el objetivo general analiza la relación entre comunicación institucional de clubes y desigualdad expresada en medios. Son dos objetos de estudio distintos.
A16: 3 | B16: G1 | C16: Objetivo general ↔ Objetivos específicos | D16: =C7 -> 1 | E16: Los tres específicos derivan del general (estrategias, representación, comparación), pero ninguno recoge la percepción de estudiantes, que es el eje del problema y la pregunta.
A17: 4 | B17: G1 | C17: Justificación ↔ Objetivo general / pregunta | D17: =C8 -> 1 | E17: La justificación argumenta sobre la percepción de estudiantes; no sustenta el análisis de contenido de publicaciones de clubes que propone el objetivo general.
A18: 5 | B18: G1 | C18: Antecedentes y marco teórico ↔ pregunta, objetivos y metodología | D18: =C9 -> 0 | E18: El marco teórico (representaciones sociales de los estudiantes) corresponde a la pregunta; la metodología (análisis de contenido de publicaciones) corresponde al objetivo general. Las dos mitades del documento no se corresponden.
A19: 1 | B19: G2 | C19: Problema ↔ Pregunta problema | D19: =D5 -> 1 | E19: El problema documenta la ausencia de una delimitación de las funciones del administrador deportivo (vacío descriptivo); la pregunta pasa a «cómo fortalecer la gestión», es decir, a una intervención no sustentada en el planteamiento.
A20: 2 | B20: G2 | C20: Pregunta problema ↔ Objetivo general | D20: =D6 -> 2 | E20: La pregunta y el objetivo general coinciden en contexto, periodo y propósito (fortalecer la gestión del desempeño del administrador).
A21: 3 | B21: G2 | C21: Objetivo general ↔ Objetivos específicos | D21: =D7 -> 1 | E21: OE1 (describir) y OE2 (estructurar estrategia) derivan del general; OE3 (evaluar la aplicación de la estrategia) exige implementarla, lo que excede el objetivo general («diseñar») y el tiempo de una monografía.
A22: 4 | B22: G2 | C22: Justificación ↔ Objetivo general / pregunta | D22: =D8 -> 1 | E22: La justificación (visibilizar y delimitar el perfil del administrador) responde al problema descriptivo, no al diseño de una estrategia de dirección.
A23: 5 | B23: G2 | C23: Antecedentes y marco teórico ↔ pregunta, objetivos y metodología | D23: =D9 -> 0 | E23: La Introducción anuncia enfoque cualitativo con entrevistas y encuestas; la sección Metodología conserva la instrucción de plantilla sobre revisión sistemática; el marco teórico no desarrolla el «modelo de gestión estratégica» que exige el objetivo general.
A24: 1 | B24: G3 | C24: Problema ↔ Pregunta problema | D24: =E5 -> 2 | E24: La pregunta recoge el vacío del problema (estrategias de marketing, sostenibilidad financiera, condiciones socioeconómicas, Patio Bonito, 2026).
A25: 2 | B25: G3 | C25: Pregunta problema ↔ Objetivo general | D25: =E6 -> 2 | E25: Pregunta y objetivo general son equivalentes en objeto, delimitación espacial y temporal.
A26: 3 | B26: G3 | C26: Objetivo general ↔ Objetivos específicos | D26: =E7 -> 1 | E26: OE1 y OE2 derivan del general; OE3 (proponer lineamientos) excede el verbo «caracterizar» y el alcance descriptivo. OE2 plantea «analizar la relación», mientras el texto aclara que no se asumirá relación causal.
A27: 4 | B27: G3 | C27: Justificación ↔ Objetivo general / pregunta | D27: =E8 -> 2 | E27: La justificación desarrolla las dimensiones académica, social y práctica y se ancla en el territorio de la pregunta.
A28: 5 | B28: G3 | C28: Antecedentes y marco teórico ↔ pregunta, objetivos y metodología | D28: =E9 -> 1 | E28: Antecedentes y brecha corresponden al objeto de estudio, pero el marco teórico solo ofrece definiciones breves; «crecimiento institucional» aparece en el marco y en la brecha, no en la pregunta ni en los objetivos.
A29: 1 | B29: G4 | C29: Problema ↔ Pregunta problema | D29: =F5 -> 2 | E29: La pregunta traduce el problema (barreras de horarios, infraestructura, convocatorias e inscripción) con población, lugar y periodo. La lista de barreras ya viene presupuesta en el problema.
A30: 2 | B30: G4 | C30: Pregunta problema ↔ Objetivo general | D30: =F6 -> 2 | E30: Pregunta y objetivo general coinciden palabra por palabra en población, lugar, periodo y dimensiones.
A31: 3 | B31: G4 | C31: Objetivo general ↔ Objetivos específicos | D31: =F7 -> 1 | E31: OE1 a OE3 son consecutivos y medibles, pero OE3 (jerarquizar) reitera el objetivo general y OE4 (proponer estrategias) excede el verbo «determinar».
A32: 4 | B32: G4 | C32: Justificación ↔ Objetivo general / pregunta | D32: =F8 -> 2 | E32: La justificación enlaza la población, la sede y la utilidad para la coordinación del torneo.
A33: 5 | B33: G4 | C33: Antecedentes y marco teórico ↔ pregunta, objetivos y metodología | D33: =F9 -> 1 | E33: El marco teórico (restricciones del ocio) y las cuatro subdimensiones corresponden a la pregunta; los antecedentes no incluyen estudios sobre torneos o deporte universitario ni evidencia colombiana; la subdimensión «equipamiento» no figura en la pregunta.
A34: 1 | B34: G5 | C34: Problema ↔ Pregunta problema | D34: =G5 -> 1 | E34: El problema trata del marketing y la visibilidad del fútbol femenino profesional (jugadoras, clubes, patrocinio); la pregunta indaga la percepción de estudiantes de Administración Deportiva.
A35: 2 | B35: G5 | C35: Pregunta problema ↔ Objetivo general | D35: =G6 -> 2 | E35: La pregunta y el objetivo general son equivalentes en población, objeto y periodo.
A36: 3 | B36: G5 | C36: Objetivo general ↔ Objetivos específicos | D36: =G7 -> 1 | E36: OE1 y OE2 desarrollan la percepción; OE3 introduce la «sostenibilidad profesional» (variable ausente en la pregunta) y OE4 es propositivo y está mal redactado («proponer estrategias… y potenciar»).
A37: 4 | B37: G5 | C37: Justificación ↔ Objetivo general / pregunta | D37: =G8 -> 1 | E37: La justificación se refiere a «las experiencias de las jugadoras» y a un periodo 2020-2026, mientras que la pregunta alude a las estudiantes y al periodo 2026-3.
A38: 5 | B38: G5 | C38: Antecedentes y marco teórico ↔ pregunta, objetivos y metodología | D38: =G9 -> 0 | E38: No hay marco teórico ni conceptual; los antecedentes no incluyen síntesis; la sección Metodología conserva la instrucción de plantilla sobre revisión sistemática, mientras que el título («narrativa») y la Introducción apuntan a experiencias de jugadoras.
A39: 1 | B39: G6 | C39: Problema ↔ Pregunta problema | D39: =H5 -> 2 | E39: La pregunta traduce el vacío formulado en el problema (relación entre calidad percibida e intención de continuar) con población, lugar y periodo.
A40: 2 | B40: G6 | C40: Pregunta problema ↔ Objetivo general | D40: =H6 -> 2 | E40: La pregunta y el objetivo general coinciden en variables, población y periodo; el verbo «analizar cuantitativamente la relación» corresponde al alcance correlacional.
A41: 3 | B41: G6 | C41: Objetivo general ↔ Objetivos específicos | D41: =H7 -> 1 | E41: Los cuatro específicos cubren el general (caracterizar, describir, establecer relación, comparar), pero OE3 y OE4 incorporan en el enunciado las pruebas estadísticas y OE4 depende de un tamaño de subgrupo que la meta de 85 respuestas no garantiza.
A42: 4 | B42: G6 | C42: Justificación ↔ Objetivo general / pregunta | D42: =H8 -> 1 | E42: La justificación enuncia la utilidad para la administración del gimnasio, pero no usa el vacío identificado ni argumenta la contribución al conocimiento; solo cita dos fuentes.
A43: 5 | B43: G6 | C43: Antecedentes y marco teórico ↔ pregunta, objetivos y metodología | D43: =H9 -> 2 | E43: Antecedentes, SERVQUAL/SERVPERF, QUESC, teoría del comportamiento planificado e hipótesis corresponden a las dos variables y a la metodología cuantitativa descritas.
A44: 1 | B44: G7 | C44: Problema ↔ Pregunta problema | D44: =I5 -> 2 | E44: La pregunta recoge la falta de evidencia sobre cómo perciben las estudiantes de Administración Deportiva (sede Bosa Porvenir) la desigualdad en su trayectoria, tal como la formula el problema.
A45: 2 | B45: G7 | C45: Pregunta problema ↔ Objetivo general | D45: =I6 -> 2 | E45: La pregunta y el objetivo general mantienen sujetos, objeto, comparación y periodo.
A46: 3 | B46: G7 | C46: Objetivo general ↔ Objetivos específicos | D46: =I7 -> 2 | E46: Los tres específicos (identificar, describir, comparar) derivan del general y se pueden verificar con una encuesta.
A47: 4 | B47: G7 | C47: Justificación ↔ Objetivo general / pregunta | D47: =I8 -> 2 | E47: La justificación declara valor teórico, utilidad metodológica y viabilidad, y se vincula con la línea base que persigue el estudio.
A48: 5 | B48: G7 | C48: Antecedentes y marco teórico ↔ pregunta, objetivos y metodología | D48: =I9 -> 1 | E48: Antecedentes y teoría respaldan el tema, pero el primer párrafo de la Referencia teórica enuncia otro objeto (desigualdad en el ingreso y la permanencia en 2026, sede Bosa) y la teoría de roles sociales se atribuye a una fuente secundaria.
A49: 1 | B49: G8 | C49: Problema ↔ Pregunta problema | D49: =J5 -> 2 | E49: La pregunta traduce el vacío del problema (ausencia de información económica sistematizada) y delimita variables, disciplina y periodo.
A50: 2 | B50: G8 | C50: Pregunta problema ↔ Objetivo general | D50: =J6 -> 2 | E50: La pregunta y el objetivo general coinciden en las tres variables y el periodo 2022-2025.
A51: 3 | B51: G8 | C51: Objetivo general ↔ Objetivos específicos | D51: =J7 -> 1 | E51: Los cuatro específicos recorren el procedimiento (identificar certámenes, caracterizar ingresos y presupuestos, describir salarios, comparar), pero el OE1 es un paso previo y el OE4 amplía el alcance a la rama masculina y a tendencias internacionales sin estar en el general.
A52: 4 | B52: G8 | C52: Justificación ↔ Objetivo general / pregunta | D52: =J8 -> 2 | E52: La justificación (teórica, social, práctica, disciplinar, viabilidad) se vincula al vacío y a las tres variables.
A53: 5 | B53: G8 | C53: Antecedentes y marco teórico ↔ pregunta, objetivos y metodología | D53: =J9 -> 2 | E53: Economía del deporte y teoría del patrocinio, más tres conceptos operativos, sustentan las variables de la pregunta; la síntesis del marco las relaciona con ella.
A54: 1 | B54: G9 | C54: Problema ↔ Pregunta problema | D54: =K5 -> 2 | E54: La pregunta recoge la necesidad de conocer la percepción de los estudiantes de tercer semestre, formulada en el contexto específico del problema.
A55: 2 | B55: G9 | C55: Pregunta problema ↔ Objetivo general | D55: =K6 -> 1 | E55: La pregunta indaga la percepción del potencial de las herramientas; el objetivo general añade conocimiento, interés, valoración y relación con competencias de formación, lo que amplía el alcance.
A56: 3 | B56: G9 | C56: Objetivo general ↔ Objetivos específicos | D56: =K7 -> 1 | E56: Los tres específicos (identificar conocimiento, describir percepción, determinar relación con la formación) derivan del general, pero cada uno incorpora varios constructos y propósitos secundarios («con el propósito de…»).
A57: 4 | B57: G9 | C57: Justificación ↔ Objetivo general / pregunta | D57: =K8 -> 1 | E57: La justificación enuncia la utilidad curricular y la escasez de estudios, pero sin ninguna fuente que la respalde.
A58: 5 | B58: G9 | C58: Antecedentes y marco teórico ↔ pregunta, objetivos y metodología | D58: =K9 -> 1 | E58: El marco teórico trata tecnología y apropiación tecnológica y el contexto institucional; los antecedentes cubren herramientas de análisis y no percepción estudiantil, y la metodología extensa de otro capítulo contradice la instrucción de revisión sistemática que permanece en la plantilla.
A59: 1 | B59: G10 | C59: Problema ↔ Pregunta problema | D59: =L5 -> 2 | E59: La pregunta recoge el vacío del apartado «Local» (ausencia de evidencia sobre la percepción de estudiantes de Administración Deportiva frente a la realidad virtual).
A60: 2 | B60: G10 | C60: Pregunta problema ↔ Objetivo general | D60: =L6 -> 2 | E60: La pregunta y el objetivo general mantienen el objeto, la población, las competencias del perfil de egreso y el periodo; el objetivo agrega la sede Bosa Porvenir.
A61: 3 | B61: G10 | C61: Objetivo general ↔ Objetivos específicos | D61: =L7 -> 2 | E61: Los tres específicos (conocimiento y familiaridad, aplicaciones pertinentes, beneficios y limitaciones) desarrollan el objetivo general en orden lógico.
A62: 4 | B62: G10 | C62: Justificación ↔ Objetivo general / pregunta | D62: =L8 -> 1 | E62: La justificación se apoya en literatura sobre realidad virtual en educación superior, pero no explicita el beneficio concreto para el programa ni la viabilidad.
A63: 5 | B63: G10 | C63: Antecedentes y marco teórico ↔ pregunta, objetivos y metodología | D63: =L9 -> 2 | E63: Aprendizaje experiencial y TAM sustentan la percepción de utilidad y facilidad de uso; los antecedentes abarcan realidad virtual en educación superior y deporte.
A64: 1 | B64: G11 | C64: Problema ↔ Pregunta problema | D64: =M5 -> 1 | E64: La pregunta (relación entre frecuencia, formato y engagement) es más específica que el problema, que no formula una situación ni cita datos; la frecuencia y el formato aparecen solo en la «Delimitación del tema».
A65: 2 | B65: G11 | C65: Pregunta problema ↔ Objetivo general | D65: =M6 -> 2 | E65: Pregunta y objetivo general son equivalentes en variables, escenario (Instagram), unidad (clubes del FPC) y periodo.
A66: 3 | B66: G11 | C66: Objetivo general ↔ Objetivos específicos | D66: =M7 -> 1 | E66: Los seis objetivos específicos recorren el procedimiento (identificar, clasificar, calcular, analizar, comparar, interpretar) y no resultados de conocimiento; el sexto no es un objetivo.
A67: 4 | B67: G11 | C67: Justificación ↔ Objetivo general / pregunta | D67: =M8 -> 1 | E67: La justificación enuncia cuatro dimensiones (pertinencia, social, académica, práctica), pero no cita ninguna fuente y su último párrafo es metodológico.
A68: 5 | B68: G11 | C68: Antecedentes y marco teórico ↔ pregunta, objetivos y metodología | D68: =M9 -> 2 | E68: El marco teórico (marketing relacional, usos y gratificaciones, engagement, frecuencia y formato) corresponde a las tres variables y a la metodología cuantitativa descritas.

Sheet Resumen por grupo
A1: Resumen por grupo
A2: Nota total, nivel, indicadores de calidad documental, fortalezas y recomendaciones de ajuste.
A4: Grupo | B4: Título del trabajo | C4: Archivo evaluado | D4: Nota total (0 – 5) | E4: Nivel | F4: Posición | G4: Ítems por debajo del umbral (de 8) | H4: Coherencia interna | I4: Hallazgos APA / redacción | J4: De gravedad alta | K4: Fortalezas | L4: Recomendaciones de ajuste
A5: G1 | B5: Percepción de la igualdad de género en el periodismo deportivo colombiano desde la perspectiva de estudiantes de Administración Deportiva | C5: G1_MI_CAP1_CAP2_V2.docx | D5: =Calificación!E47 -> 2.35625 | E5: =Calificación!E48 -> En desarrollo | F5: =RANK(D5,$D$5:$D$15,0) -> 10 | G5: =COUNTIF(Calificación!E39:E46,"<"&Rúbrica!$D$6) -> 5 | H5: ='Coherencia interna'!C10 -> 0.3 | I5: ='Errores APA y redacción'!B14 -> 8 | J5: ='Errores APA y redacción'!B18 -> 2 | K5: Población y fenómeno bien delimitados en el problema; antecedentes con estructura reconocible; fuentes indexadas; reconocimiento explícito de la limitación de generalización. | L5: 1) Decidir un único objeto de estudio (percepción de estudiantes o análisis de contenido) y reescribir pregunta, objetivos, justificación, marco teórico y metodología en torno a él. 2) Depurar la lista de referencias: citar o retirar las 8 huérfanas e incluir las 4 faltantes. 3) Incorporar cifras colombianas y locales y las causas y consecuencias de la desigualdad. 4) Cerrar los antecedentes con una síntesis y la brecha. 5) Retirar los textos de plantilla y unificar la declaración de IA con herramienta, versión y fecha.
A6: G2 | B6: El papel de la administración deportiva en las escuelas de fútbol | C6: G2_MI_Cap2_V2_06_Oct_2026.docx | D6: =Calificación!F47 -> 3.03875 | E6: =Calificación!F48 -> Satisfactorio | F6: =RANK(D6,$D$5:$D$15,0) -> 8 | G6: =COUNTIF(Calificación!F39:F46,"<"&Rúbrica!$D$6) -> 4 | H6: ='Coherencia interna'!D10 -> 0.5 | I6: ='Errores APA y redacción'!C14 -> 10 | J6: ='Errores APA y redacción'!C18 -> 1 | K6: Descripción del problema en tres niveles con datos cuantitativos y vacío explícito; antecedentes con síntesis y brecha; delimitación de lugar y periodo; uso de fuentes indexadas recientes (Retos, Pensamiento & Gestión). | L6: 1) Reformular la pregunta y el objetivo general como caracterización (p. ej., ¿cuáles son las funciones que desempeña el administrador…?) o conservar el diseño de estrategia y retirar el OE3. 2) Dividir el OE1 en un único objeto. 3) Sustentar la justificación con fuentes. 4) Agregar un marco teórico (teoría administrativa y modelo de gestión estratégica) y corregir el conteo de funciones. 5) Reescribir la Introducción, unificar la metodología (cualitativa descriptiva o revisión sistemática) y corregir la lista de referencias (Ley 181, Pedreros/Pedrosa, Resolución 639).
A7: G3 | B7: El marketing deportivo como estrategia para la sostenibilidad financiera de escuelas de formación deportiva de Patio Bonito | C7: G3_Avance_Marco_Teórico.docx | D7: =Calificación!G47 -> 3.67125 | E7: =Calificación!G48 -> Satisfactorio | F7: =RANK(D7,$D$5:$D$15,0) -> 4 | G7: =COUNTIF(Calificación!G39:G46,"<"&Rúbrica!$D$6) -> 2 | H7: ='Coherencia interna'!E10 -> 0.8 | I7: ='Errores APA y redacción'!D14 -> 9 | J7: ='Errores APA y redacción'!D18 -> 4 | K7: Planteamiento más coherente entre pregunta y objetivo general; descripción del problema en tres niveles con datos territoriales; antecedentes con comparación crítica, síntesis y brecha; redacción prudente que evita asumir causalidad. | L7: 1) Aportar evidencia del problema en las escuelas (número, financiación, deserción) y sus causas y consecuencias. 2) Ajustar OE2 y OE3 al alcance descriptivo o ampliar el OG a «proponer». 3) Convertir el marco conceptual en teórico: desarrollar Fullerton y Merz (2008) u otro modelo de marketing, y definir sostenibilidad financiera y condiciones socioeconómicas con fuentes. 4) Reconstruir la lista de referencias con autor corporativo y fecha para todas las páginas web, unificar Torres/Pachau Torres y corregir los paréntesis. 5) Retirar el contenido de plantilla.
A8: G4 | B8: Barreras logísticas que limitan la participación de los estudiantes de primer a tercer semestre de Administración Deportiva en el torneo interno de microfútbol de la Sede Bosa Porvenir (2026-3) | C8: G4-MI-Avance.docx | D8: =Calificación!H47 -> 3.595 | E8: =Calificación!H48 -> Satisfactorio | F8: =RANK(D8,$D$5:$D$15,0) -> 5 | G8: =COUNTIF(Calificación!H39:H46,"<"&Rúbrica!$D$6) -> 2 | H8: ='Coherencia interna'!F10 -> 0.8 | I8: ='Errores APA y redacción'!E14 -> 11 | J8: ='Errores APA y redacción'!E18 -> 3 | K8: Pregunta y objetivo general precisos y alineados; selección de la teoría de restricciones del ocio acorde con el fenómeno; antecedentes organizados por temas con tabla resumen, límites de evidencia y vacío; justificación con destinatarios claros. | L8: 1) Reestructurar el problema en los tres niveles, retirar los encabezados de guion, aportar datos de la sede (inscripciones, partidos por W) y corregir la atribución de cifras a Sevil Serrano et al. y Franco-Idárraga et al. 2) Formular el vacío en el problema. 3) Eliminar el OE3 por duplicidad y el OE4 o ajustar el general a «proponer». 4) Fundamentar la logística deportiva con fuentes y sustituir las que no respaldan la afirmación. 5) Incluir antecedentes de deporte universitario y colombianos. 6) Depurar la lista de referencias (duplicados, orden, autores repetidos) y el contenido de plantilla.
A9: G5 | B9: Desarrollo e implementación del marketing deportivo en el fútbol colombiano: una narrativa de la realidad | C9: G5_MI_CAP1_CAP2_V2.docx | D9: =Calificación!I47 -> 2.145 | E9: =Calificación!I48 -> En desarrollo | F9: =RANK(D9,$D$5:$D$15,0) -> 11 | G9: =COUNTIF(Calificación!I39:I46,"<"&Rúbrica!$D$6) -> 6 | H9: ='Coherencia interna'!G10 -> 0.5 | I9: ='Errores APA y redacción'!F14 -> 11 | J9: ='Errores APA y redacción'!F18 -> 6 | K9: Pregunta y objetivo general alineados y con delimitación; intento de organizar el problema en tres niveles; reconocimiento de la naturaleza descriptiva del alcance en la delimitación («no generalizar»). | L9: 1) Definir quién aporta la información (jugadoras o estudiantes) y reformular pregunta, objetivos, justificación y título en consecuencia; modificar el título para diferenciarlo del trabajo de Clavijo Vidal y Vidal Cañas (2021). 2) Incluir en las referencias todas las fuentes institucionales citadas, con autor corporativo, año y enlace. 3) Verificar y corregir las cifras de la sección de magnitud en la fuente primaria. 4) Reescribir las consecuencias en prosa académica. 5) Construir un marco teórico (marketing deportivo, visibilidad mediática, patrocinio) con autores académicos y completar los antecedentes con objetivo, método, resultado, síntesis y vacío.
A10: G6 | B10: ¿Cómo se asocia la percepción de la calidad del servicio del gimnasio de la Universidad Distrital (sede Bosa–Porvenir) con la intención de continuar utilizándolo en estudiantes usuarios de 18 a 25 años? (2026-3) | C10: G6_Cap1_a_Cap5.docx | D10: =Calificación!J47 -> 4.22375 | E10: =Calificación!J48 -> Alto | F10: =RANK(D10,$D$5:$D$15,0) -> 3 | G10: =COUNTIF(Calificación!J39:J46,"<"&Rúbrica!$D$6) -> 1 | H10: ='Coherencia interna'!H10 -> 0.8 | I10: ='Errores APA y redacción'!G14 -> 8 | J10: ='Errores APA y redacción'!G18 -> 0 | K10: Trabajo más completo del curso: pregunta, objetivo general y marco teórico alineados con un diseño cuantitativo correlacional; antecedentes con muestra, método y aporte; vacío explícito; declaración de IA con herramienta, modelo, fecha, propósito y verificación; lista de referencias consistente con las citas. | L10: 1) Reformular la pregunta como relación («¿Qué relación existe…?») y acortar el título. 2) Trasladar a la metodología las técnicas estadísticas de los OE3 y OE4 y corregir la incompatibilidad entre la meta de 85 respuestas y los subgrupos de 30. 3) Fortalecer la justificación con el vacío, beneficiarios y fuentes. 4) Aportar datos del gimnasio (usuarios, asistencia) solicitados a Bienestar Universitario. 5) Retirar las marcas [COMPLETAR], [CONFIRMAR] y [firmas], y el Anexo G.
A11: G7 | B11: Desigualdad de género en la trayectoria académica: percepciones en Administración Deportiva | C11: G7_MI_30SEP_CAP2.docx | D11: =Calificación!K47 -> 4.395 | E11: =Calificación!K48 -> Alto | F11: =RANK(D11,$D$5:$D$15,0) -> 1 | G11: =COUNTIF(Calificación!K39:K46,"<"&Rúbrica!$D$6) -> 0 | H11: ='Coherencia interna'!I10 -> 0.9 | I11: ='Errores APA y redacción'!H14 -> 9 | J11: ='Errores APA y redacción'!H18 -> 2 | K11: Planteamiento explícito del problema como falta de evidencia; pregunta, objetivo general y objetivos específicos bien alineados; justificación con valor teórico, utilidad metodológica y viabilidad; marco teórico con cautelas sobre la transferencia de los hallazgos; antecedentes con vacío formulado. | L11: 1) Trasladar a la Descripción del problema la estructura internacional-nacional-local y reducir el marco normativo de la Introducción. 2) Completar las referencias (cuatro antecedentes y UD 2026b), depurar los duplicados y retirar las no citadas. 3) Unificar el objeto del primer párrafo de la Referencia teórica con la pregunta y definir allí desigualdad de género y trayectoria académica. 4) Retirar el metacomentario de los objetivos, la nota pendiente, «el autor» y «anteproyecto». 5) Corregir la declaración de IA (plural, modelo y fechas).
A12: G8 | B12: Evolución económica del baloncesto profesional femenino en Colombia (2022–2025) | C12: G8 Avances cap 2.docx | D12: =Calificación!L47 -> 4.36125 | E12: =Calificación!L48 -> Alto | F12: =RANK(D12,$D$5:$D$15,0) -> 2 | G12: =COUNTIF(Calificación!L39:L46,"<"&Rúbrica!$D$6) -> 0 | H12: ='Coherencia interna'!J10 -> 0.9 | I12: ='Errores APA y redacción'!I14 -> 9 | J12: ='Errores APA y redacción'!I18 -> 3 | K12: Planteamiento más documentado del curso (cuatro niveles, tres tablas, actores afectados y vacío); pregunta y objetivo general coherentes; justificación con entregables y viabilidad; marco teórico con fuentes de base y síntesis; reconocimiento explícito de límites de los datos. | L12: 1) Verificar la existencia y disponibilidad de datos antes de comprometer la pregunta; si no hay baloncesto femenino profesional contratado formalmente, reformular el objeto o la unidad de análisis. 2) Retirar el método del OG y reubicar el OE1 como actividad metodológica; ajustar o suprimir el OE4. 3) Sustituir la prensa por la fuente primaria (informe de la SIC, estados financieros de la Superintendencia) y reconciliar el dato de «futbolistas». 4) Añadir sufijos a/b en Ministerio del Deporte (2023) y FIBA (2025). 5) Incorporar la Declaración de uso de IA con herramienta, modelo, fecha y alcance. 6) Reducir el nivel de detalle del problema.
A13: G9 | B13: Percepción de los estudiantes de Administración Deportiva sobre el potencial de las herramientas tecnológicas para el análisis táctico y la gestión del rendimiento en el fútbol profesional (2026) | C13: G9_MI_Capitulo_3.docx | D13: =Calificación!M47 -> 2.36 | E13: =Calificación!M48 -> En desarrollo | F13: =RANK(D13,$D$5:$D$15,0) -> 9 | G13: =COUNTIF(Calificación!M39:M46,"<"&Rúbrica!$D$6) -> 5 | H13: ='Coherencia interna'!K10 -> 0.6 | I13: ='Errores APA y redacción'!J14 -> 12 | J13: ='Errores APA y redacción'!J18 -> 8 | K13: Pregunta bien delimitada; marco teórico organizado en tres categorías con revisiones indexadas recientes; inclusión de criterios de evaluación de fuentes (tabla CRAAP); referencias con DOI en los artículos. | L13: 1) Reescribir la Introducción en prosa académica y sustentar los niveles internacional, nacional y local con al menos una fuente distinta por nivel, incluyendo datos de magnitud. 2) Acotar el OG y los OE (un constructo y un propósito cada uno). 3) Sustentar la justificación con fuentes y retirar adjetivos promocionales. 4) Ampliar los antecedentes (percepción de estudiantes, formación en analítica deportiva), con síntesis y vacío; incorporar Davidson et al. (2024). 5) Corregir las referencias: Vuorikari et al. (2022), autores corporativos para las páginas web, entrada corrupta de la APA y fuente oficial de la Ley 181. 6) Corregir la portada, retirar la plantilla y completar la declaración de IA.
A14: G10 | B14: Percepción de estudiantes de Administración Deportiva sobre el uso de realidad virtual para el desarrollo de competencias profesionales | C14: G10_Capítulo 2_Avance_Metodología de Investigación.docx | D14: =Calificación!N47 -> 3.56 | E14: =Calificación!N48 -> Satisfactorio | F14: =RANK(D14,$D$5:$D$15,0) -> 6 | G14: =COUNTIF(Calificación!N39:N46,"<"&Rúbrica!$D$6) -> 2 | H14: ='Coherencia interna'!L10 -> 0.9 | I14: ='Errores APA y redacción'!K14 -> 9 | J14: ='Errores APA y redacción'!K18 -> 5 | K14: Redacción formal y consistente; pregunta, objetivo general y objetivos específicos alineados; antecedentes con la misma estructura en los tres niveles, que indican en cada caso la diferencia frente al estudio; marco teórico con fuentes de base (Kolb, Davis) y esquema de relación. | L14: 1) Replantear el problema como una necesidad formativa documentada (competencias, oferta curricular, brecha), con datos de magnitud, causas y consecuencias. 2) Especificar las competencias del perfil de egreso y definir la población (semestres, experiencia con realidad virtual). 3) Reformular el verbo «reconocer» y retirar el método del OE2. 4) Fortalecer los antecedentes nacionales y locales con estudios sobre educación en gestión deportiva y cerrar con una síntesis y la brecha. 5) Corregir las citas de Cabrera-Duffaut et al. (2024) y Salgado García y Fernández Gualteros (2024); eliminar duplicados y parámetros utm. 6) Redactar una Declaración de IA completa.
A15: G11 | B15: Marketing deportivo en el fútbol: estrategias digitales y engagement de los aficionados | C15: G11_MI_10oct_Cap2_V2.docx | D15: =Calificación!O47 -> 3.54 | E15: =Calificación!O48 -> Satisfactorio | F15: =RANK(D15,$D$5:$D$15,0) -> 7 | G15: =COUNTIF(Calificación!O39:O46,"<"&Rúbrica!$D$6) -> 1 | H15: ='Coherencia interna'!M10 -> 0.7 | I15: ='Errores APA y redacción'!L14 -> 8 | J15: ='Errores APA y redacción'!L18 -> 2 | K15: Pregunta, objetivo general y marco teórico bien articulados con un diseño cuantitativo correlacional; marco teórico con aclaración de las limitaciones de la medición; lista de referencias con formato APA 7 y DOI en todas las entradas. | L15: 1) Reescribir la Descripción del problema con datos (número de clubes, seguidores, publicaciones, inversión en comunicación), fuentes en los niveles nacional y local, causas y consecuencias. 2) Condensar los seis objetivos en tres de conocimiento y retirar «Interpretar». 3) Sustentar la justificación con fuentes y retirar el párrafo metodológico. 4) Incorporar antecedentes colombianos y latinoamericanos y usar las revisiones de 2023-2025 que ya están en la lista, o retirarlas. 5) Unificar el año de Romero-Jara et al. y verificar qué atribuye cada estudio. 6) Retirar la plantilla y el lenguaje de proceso, y completar la Declaración de IA.

Sheet Declaración de IA
A1: Declaración de uso de inteligencia artificial generativa
A2: Conforme a APA 7 y a la práctica de transparencia académica.
A4: Herramienta y modelo | B4: Claude (Anthropic), modelo Claude Sonnet 5.5 (identificador claude-sonnet-5-5), ejecutado en el entorno Claude Code. Fecha de uso: 19 de octubre de 2026.
A5: Solicitud | B5: Evaluación de 11 documentos de estudiantes según criterios metodológicos para la descripción del problema, la pregunta, los objetivos, la justificación y el capítulo 2, considerando redacción y normas APA 7.ª edición, por solicitud del profesor Kilderman Mendoza Moreno.
A6: Usos | B6: Lectura y extracción de texto de los .docx; comprobación automatizada de la correspondencia entre citas y referencias; propuesta de codificación de 31 indicadores por grupo; redacción de los comentarios cualitativos; construcción del libro de Excel con fórmulas.
A7: Verificaciones realizadas | B7: Se consultaron en línea tres puntos: la muestra del estudio de Sevil Serrano et al. (citado en G4), los autores del marco DigComp 2.2 (G9) y los tres autores de Cabrera-Duffaut (G10). El resto de los hallazgos se basa en la lectura del texto de cada documento y en el script de correspondencia cita–referencia, con revisión manual de los falsos positivos.
A8: Limitaciones | B8: No se usó software antiplagio; las observaciones de originalidad (por ejemplo, la semejanza de título señalada en G5) se apoyan solo en la lista de referencias del propio documento. Las referencias no consultadas en línea no se contrastaron con la fuente. Las codificaciones 0 / 1 / 2 y los pesos son juicios propuestos que requieren validación del profesor antes de su uso para calificar.
A9: Responsabilidad | B9: La decisión final sobre las notas y la retroalimentación a los estudiantes corresponde al profesor. El contenido generado debe ser revisado antes de ser compartido.
